<?xml version="1.0" encoding="UTF-8" standalone="yes"?>
<w:document xmlns:wpc="http://schemas.microsoft.com/office/word/2010/wordprocessingCanvas" xmlns:cx="http://schemas.microsoft.com/office/drawing/2014/chartex" xmlns:cx1="http://schemas.microsoft.com/office/drawing/2015/9/8/chartex" xmlns:cx2="http://schemas.microsoft.com/office/drawing/2015/10/21/chartex" xmlns:cx3="http://schemas.microsoft.com/office/drawing/2016/5/9/chartex" xmlns:cx4="http://schemas.microsoft.com/office/drawing/2016/5/10/chartex" xmlns:cx5="http://schemas.microsoft.com/office/drawing/2016/5/11/chartex" xmlns:cx6="http://schemas.microsoft.com/office/drawing/2016/5/12/chartex" xmlns:cx7="http://schemas.microsoft.com/office/drawing/2016/5/13/chartex" xmlns:cx8="http://schemas.microsoft.com/office/drawing/2016/5/14/chartex" xmlns:mc="http://schemas.openxmlformats.org/markup-compatibility/2006" xmlns:aink="http://schemas.microsoft.com/office/drawing/2016/ink" xmlns:am3d="http://schemas.microsoft.com/office/drawing/2017/model3d" xmlns:o="urn:schemas-microsoft-com:office:office" xmlns:oel="http://schemas.microsoft.com/office/2019/extlst" xmlns:r="http://schemas.openxmlformats.org/officeDocument/2006/relationships" xmlns:m="http://schemas.openxmlformats.org/officeDocument/2006/math" xmlns:v="urn:schemas-microsoft-com:vml" xmlns:wp14="http://schemas.microsoft.com/office/word/2010/wordprocessingDrawing" xmlns:wp="http://schemas.openxmlformats.org/drawingml/2006/wordprocessingDrawing" xmlns:w10="urn:schemas-microsoft-com:office:word" xmlns:w="http://schemas.openxmlformats.org/wordprocessingml/2006/main" xmlns:w14="http://schemas.microsoft.com/office/word/2010/wordml" xmlns:w15="http://schemas.microsoft.com/office/word/2012/wordml" xmlns:w16cex="http://schemas.microsoft.com/office/word/2018/wordml/cex" xmlns:w16cid="http://schemas.microsoft.com/office/word/2016/wordml/cid" xmlns:w16="http://schemas.microsoft.com/office/word/2018/wordml" xmlns:w16du="http://schemas.microsoft.com/office/word/2023/wordml/word16du" xmlns:w16sdtdh="http://schemas.microsoft.com/office/word/2020/wordml/sdtdatahash" xmlns:w16sdtfl="http://schemas.microsoft.com/office/word/2024/wordml/sdtformatlock" xmlns:w16se="http://schemas.microsoft.com/office/word/2015/wordml/symex" xmlns:wpg="http://schemas.microsoft.com/office/word/2010/wordprocessingGroup" xmlns:wpi="http://schemas.microsoft.com/office/word/2010/wordprocessingInk" xmlns:wne="http://schemas.microsoft.com/office/word/2006/wordml" xmlns:wps="http://schemas.microsoft.com/office/word/2010/wordprocessingShape" mc:Ignorable="w14 w15 w16se w16cid w16 w16cex w16sdtdh w16sdtfl w16du wp14"><w:body><w:p w14:paraId="086B0C4C" w14:textId="26D32DF0" w:rsidR="002C1B5F" w:rsidRPr="002C1B5F" w:rsidRDefault="002C1B5F" w:rsidP="001F3E92"><w:pPr><w:jc w:val="center"/><w:rPr><w:b/><w:bCs/><w:sz w:val="28"/><w:szCs w:val="28"/></w:rPr></w:pPr><w:r w:rsidRPr="002C1B5F"><w:rPr><w:b/><w:bCs/><w:sz w:val="28"/><w:szCs w:val="28"/><w:highlight w:val="yellow"/></w:rPr><w:t>Project Title</w:t></w:r></w:p><w:p w14:paraId="0DC365FA" w14:textId="77777777" w:rsidR="002C1B5F" w:rsidRPr="002C1B5F" w:rsidRDefault="002C1B5F" w:rsidP="002C1B5F"><w:r w:rsidRPr="002C1B5F"><w:rPr><w:b/><w:bCs/></w:rPr><w:t>Automated File Upload Pipeline from Local Folder to S3 → Lambda → RDS → SNS</w:t></w:r></w:p><w:p w14:paraId="1C2BDB4C" w14:textId="77777777" w:rsidR="002C1B5F" w:rsidRPr="002C1B5F" w:rsidRDefault="0031267B" w:rsidP="002C1B5F"><w:r><w:pict w14:anchorId="6109570D"><v:rect id="_x0000_i1025" style="width:0;height:1.5pt" o:hralign="center" o:hrstd="t" o:hr="t" fillcolor="#a0a0a0" stroked="f"/></w:pict></w:r></w:p><w:p w14:paraId="5988C448" w14:textId="77777777" w:rsidR="002C1B5F" w:rsidRPr="002C1B5F" w:rsidRDefault="002C1B5F" w:rsidP="001F3E92"><w:pPr><w:jc w:val="center"/><w:rPr><w:b/><w:bCs/><w:sz w:val="28"/><w:szCs w:val="28"/></w:rPr></w:pPr><w:r w:rsidRPr="002C1B5F"><w:rPr><w:b/><w:bCs/><w:sz w:val="28"/><w:szCs w:val="28"/><w:highlight w:val="yellow"/></w:rPr><w:t>Introduction</w:t></w:r></w:p><w:p w14:paraId="6EDED78B" w14:textId="77777777" w:rsidR="002C1B5F" w:rsidRPr="002C1B5F" w:rsidRDefault="002C1B5F" w:rsidP="002C1B5F"><w:r w:rsidRPr="002C1B5F"><w:t>This project focuses on designing and implementing an event-driven file ingestion pipeline on AWS. The system automatically uploads files from a local machine to an S3 bucket, processes them using Lambda, inserts the data into an RDS database, and triggers notifications via SNS.</w:t></w:r></w:p><w:p w14:paraId="75FFE415" w14:textId="77777777" w:rsidR="002C1B5F" w:rsidRPr="002C1B5F" w:rsidRDefault="002C1B5F" w:rsidP="002C1B5F"><w:r w:rsidRPr="002C1B5F"><w:t>The implementation demonstrates how AWS services such as S3, Lambda, RDS, SNS, CloudWatch, and IAM can work together to provide a scalable, automated, and reliable data pipeline.</w:t></w:r></w:p><w:p w14:paraId="74DDEBBE" w14:textId="77777777" w:rsidR="002C1B5F" w:rsidRPr="002C1B5F" w:rsidRDefault="0031267B" w:rsidP="002C1B5F"><w:r><w:pict w14:anchorId="3E5D7918"><v:rect id="_x0000_i1026" style="width:0;height:1.5pt" o:hralign="center" o:hrstd="t" o:hr="t" fillcolor="#a0a0a0" stroked="f"/></w:pict></w:r></w:p><w:p w14:paraId="00A9CA71" w14:textId="77777777" w:rsidR="002C1B5F" w:rsidRPr="002C1B5F" w:rsidRDefault="002C1B5F" w:rsidP="001F3E92"><w:pPr><w:jc w:val="center"/><w:rPr><w:b/><w:bCs/><w:sz w:val="28"/><w:szCs w:val="28"/></w:rPr></w:pPr><w:r w:rsidRPr="002C1B5F"><w:rPr><w:b/><w:bCs/><w:sz w:val="28"/><w:szCs w:val="28"/><w:highlight w:val="yellow"/></w:rPr><w:t>Objectives</w:t></w:r></w:p><w:p w14:paraId="0CC8129E" w14:textId="77777777" w:rsidR="002C1B5F" w:rsidRPr="002C1B5F" w:rsidRDefault="002C1B5F" w:rsidP="001F3E92"><w:pPr><w:numPr><w:ilvl w:val="0"/><w:numId w:val="1"/></w:numPr><w:spacing w:line="240" w:lineRule="auto"/></w:pPr><w:r w:rsidRPr="002C1B5F"><w:t>Upload files from a local machine to Amazon S3 automatically.</w:t></w:r></w:p><w:p w14:paraId="727EE866" w14:textId="77777777" w:rsidR="002C1B5F" w:rsidRPr="002C1B5F" w:rsidRDefault="002C1B5F" w:rsidP="001F3E92"><w:pPr><w:numPr><w:ilvl w:val="0"/><w:numId w:val="1"/></w:numPr><w:spacing w:line="240" w:lineRule="auto"/></w:pPr><w:r w:rsidRPr="002C1B5F"><w:t>Trigger a Lambda function upon file upload.</w:t></w:r></w:p><w:p w14:paraId="09A694D2" w14:textId="77777777" w:rsidR="002C1B5F" w:rsidRPr="002C1B5F" w:rsidRDefault="002C1B5F" w:rsidP="001F3E92"><w:pPr><w:numPr><w:ilvl w:val="0"/><w:numId w:val="1"/></w:numPr><w:spacing w:line="240" w:lineRule="auto"/></w:pPr><w:r w:rsidRPr="002C1B5F"><w:t>Parse CSV files and insert data into an RDS database.</w:t></w:r></w:p><w:p w14:paraId="56A7EC9E" w14:textId="77777777" w:rsidR="002C1B5F" w:rsidRPr="002C1B5F" w:rsidRDefault="002C1B5F" w:rsidP="001F3E92"><w:pPr><w:numPr><w:ilvl w:val="0"/><w:numId w:val="1"/></w:numPr><w:spacing w:line="240" w:lineRule="auto"/></w:pPr><w:r w:rsidRPr="002C1B5F"><w:t>Send success or failure notifications via SNS.</w:t></w:r></w:p><w:p w14:paraId="032D4950" w14:textId="77777777" w:rsidR="002C1B5F" w:rsidRPr="002C1B5F" w:rsidRDefault="002C1B5F" w:rsidP="001F3E92"><w:pPr><w:numPr><w:ilvl w:val="0"/><w:numId w:val="1"/></w:numPr><w:spacing w:line="240" w:lineRule="auto"/></w:pPr><w:r w:rsidRPr="002C1B5F"><w:t>Log all operations in CloudWatch for monitoring and debugging.</w:t></w:r></w:p><w:p w14:paraId="7B62225A" w14:textId="77777777" w:rsidR="002C1B5F" w:rsidRPr="002C1B5F" w:rsidRDefault="002C1B5F" w:rsidP="001F3E92"><w:pPr><w:numPr><w:ilvl w:val="0"/><w:numId w:val="1"/></w:numPr><w:spacing w:line="240" w:lineRule="auto"/></w:pPr><w:r w:rsidRPr="002C1B5F"><w:t>Apply least-privilege IAM permissions for secure access.</w:t></w:r></w:p><w:p w14:paraId="7ECCE1E9" w14:textId="77777777" w:rsidR="002C1B5F" w:rsidRPr="002C1B5F" w:rsidRDefault="0031267B" w:rsidP="002C1B5F"><w:r><w:pict w14:anchorId="22FB72B9"><v:rect id="_x0000_i1027" style="width:0;height:1.5pt" o:hralign="center" o:hrstd="t" o:hr="t" fillcolor="#a0a0a0" stroked="f"/></w:pict></w:r></w:p><w:p w14:paraId="1503AB4C" w14:textId="77777777" w:rsidR="002C1B5F" w:rsidRDefault="002C1B5F" w:rsidP="001F3E92"><w:pPr><w:jc w:val="center"/><w:rPr><w:b/><w:bCs/><w:sz w:val="28"/><w:szCs w:val="28"/></w:rPr></w:pPr><w:r w:rsidRPr="002C1B5F"><w:rPr><w:b/><w:bCs/><w:sz w:val="28"/><w:szCs w:val="28"/><w:highlight w:val="yellow"/></w:rPr><w:t>AWS Services Used</w:t></w:r></w:p><w:tbl><w:tblPr><w:tblStyle w:val="TableGrid"/><w:tblW w:w="10207" w:type="dxa"/><w:tblInd w:w="-431" w:type="dxa"/><w:tblLook w:val="04A0" w:firstRow="1" w:lastRow="0" w:firstColumn="1" w:lastColumn="0" w:noHBand="0" w:noVBand="1"/></w:tblPr><w:tblGrid><w:gridCol w:w="3545"/><w:gridCol w:w="6662"/></w:tblGrid><w:tr w:rsidR="001F3E92" w14:paraId="3E93E58C" w14:textId="77777777" w:rsidTr="001F3E92"><w:tc><w:tcPr><w:tcW w:w="3545" w:type="dxa"/><w:vAlign w:val="center"/></w:tcPr><w:p w14:paraId="35360143" w14:textId="081D5C60" w:rsidR="001F3E92" w:rsidRDefault="001F3E92" w:rsidP="001F3E92"><w:pPr><w:jc w:val="center"/><w:rPr><w:b/><w:bCs/><w:sz w:val="28"/><w:szCs w:val="28"/></w:rPr></w:pPr><w:r w:rsidRPr="002C1B5F"><w:rPr><w:b/><w:bCs/></w:rPr><w:t>Service</w:t></w:r></w:p></w:tc><w:tc><w:tcPr><w:tcW w:w="6662" w:type="dxa"/><w:vAlign w:val="center"/></w:tcPr><w:p w14:paraId="73DB4931" w14:textId="57404639" w:rsidR="001F3E92" w:rsidRDefault="001F3E92" w:rsidP="001F3E92"><w:pPr><w:jc w:val="center"/><w:rPr><w:b/><w:bCs/><w:sz w:val="28"/><w:szCs w:val="28"/></w:rPr></w:pPr><w:r w:rsidRPr="002C1B5F"><w:rPr><w:b/><w:bCs/></w:rPr><w:t>Purpose / Functionality</w:t></w:r></w:p></w:tc></w:tr><w:tr w:rsidR="001F3E92" w14:paraId="2DCE75A1" w14:textId="77777777" w:rsidTr="001F3E92"><w:tc><w:tcPr><w:tcW w:w="3545" w:type="dxa"/><w:vAlign w:val="center"/></w:tcPr><w:p w14:paraId="4AD9F25E" w14:textId="111653EA" w:rsidR="001F3E92" w:rsidRDefault="001F3E92" w:rsidP="001F3E92"><w:pPr><w:jc w:val="center"/><w:rPr><w:b/><w:bCs/><w:sz w:val="28"/><w:szCs w:val="28"/></w:rPr></w:pPr><w:r w:rsidRPr="002C1B5F"><w:t>Amazon S3</w:t></w:r></w:p></w:tc><w:tc><w:tcPr><w:tcW w:w="6662" w:type="dxa"/><w:vAlign w:val="center"/></w:tcPr><w:p w14:paraId="2633D711" w14:textId="209E04D0" w:rsidR="001F3E92" w:rsidRDefault="001F3E92" w:rsidP="001F3E92"><w:pPr><w:jc w:val="center"/><w:rPr><w:b/><w:bCs/><w:sz w:val="28"/><w:szCs w:val="28"/></w:rPr></w:pPr><w:r w:rsidRPr="002C1B5F"><w:t>Stores uploaded files from the local machine.</w:t></w:r></w:p></w:tc></w:tr><w:tr w:rsidR="001F3E92" w14:paraId="20FD41DC" w14:textId="77777777" w:rsidTr="001F3E92"><w:tc><w:tcPr><w:tcW w:w="3545" w:type="dxa"/><w:vAlign w:val="center"/></w:tcPr><w:p w14:paraId="64835BC8" w14:textId="692B5A01" w:rsidR="001F3E92" w:rsidRDefault="001F3E92" w:rsidP="001F3E92"><w:pPr><w:jc w:val="center"/><w:rPr><w:b/><w:bCs/><w:sz w:val="28"/><w:szCs w:val="28"/></w:rPr></w:pPr><w:r><w:t>A</w:t></w:r><w:r w:rsidRPr="002C1B5F"><w:t>WS Lambda</w:t></w:r></w:p></w:tc><w:tc><w:tcPr><w:tcW w:w="6662" w:type="dxa"/><w:vAlign w:val="center"/></w:tcPr><w:p w14:paraId="1E64EDA3" w14:textId="3F28CC47" w:rsidR="001F3E92" w:rsidRDefault="001F3E92" w:rsidP="001F3E92"><w:pPr><w:jc w:val="center"/><w:rPr><w:b/><w:bCs/><w:sz w:val="28"/><w:szCs w:val="28"/></w:rPr></w:pPr><w:r w:rsidRPr="002C1B5F"><w:t>Processes CSV files and inserts data into RDS.</w:t></w:r></w:p></w:tc></w:tr><w:tr w:rsidR="001F3E92" w14:paraId="1092CA29" w14:textId="77777777" w:rsidTr="001F3E92"><w:tc><w:tcPr><w:tcW w:w="3545" w:type="dxa"/><w:vAlign w:val="center"/></w:tcPr><w:p w14:paraId="2ED45EE1" w14:textId="1B31998F" w:rsidR="001F3E92" w:rsidRDefault="001F3E92" w:rsidP="001F3E92"><w:pPr><w:jc w:val="center"/><w:rPr><w:b/><w:bCs/><w:sz w:val="28"/><w:szCs w:val="28"/></w:rPr></w:pPr><w:r w:rsidRPr="002C1B5F"><w:t>Amazon RDS</w:t></w:r></w:p></w:tc><w:tc><w:tcPr><w:tcW w:w="6662" w:type="dxa"/><w:vAlign w:val="center"/></w:tcPr><w:p w14:paraId="24489BEE" w14:textId="58DCCDA7" w:rsidR="001F3E92" w:rsidRDefault="001F3E92" w:rsidP="001F3E92"><w:pPr><w:jc w:val="center"/><w:rPr><w:b/><w:bCs/><w:sz w:val="28"/><w:szCs w:val="28"/></w:rPr></w:pPr><w:r w:rsidRPr="002C1B5F"><w:t>Stores structured data for analytics and reporting.</w:t></w:r></w:p></w:tc></w:tr><w:tr w:rsidR="001F3E92" w14:paraId="10384B5F" w14:textId="77777777" w:rsidTr="001F3E92"><w:tc><w:tcPr><w:tcW w:w="3545" w:type="dxa"/><w:vAlign w:val="center"/></w:tcPr><w:p w14:paraId="6A62526C" w14:textId="29CA5D2E" w:rsidR="001F3E92" w:rsidRDefault="001F3E92" w:rsidP="001F3E92"><w:pPr><w:jc w:val="center"/><w:rPr><w:b/><w:bCs/><w:sz w:val="28"/><w:szCs w:val="28"/></w:rPr></w:pPr><w:r w:rsidRPr="002C1B5F"><w:t>Amazon SNS</w:t></w:r></w:p></w:tc><w:tc><w:tcPr><w:tcW w:w="6662" w:type="dxa"/><w:vAlign w:val="center"/></w:tcPr><w:p w14:paraId="5900D6AB" w14:textId="53657B90" w:rsidR="001F3E92" w:rsidRDefault="001F3E92" w:rsidP="001F3E92"><w:pPr><w:jc w:val="center"/><w:rPr><w:b/><w:bCs/><w:sz w:val="28"/><w:szCs w:val="28"/></w:rPr></w:pPr><w:r w:rsidRPr="002C1B5F"><w:t>Sends notifications on pipeline success or failure.</w:t></w:r></w:p></w:tc></w:tr><w:tr w:rsidR="001F3E92" w14:paraId="10F5A7ED" w14:textId="77777777" w:rsidTr="001F3E92"><w:tc><w:tcPr><w:tcW w:w="3545" w:type="dxa"/><w:vAlign w:val="center"/></w:tcPr><w:p w14:paraId="5AB0288B" w14:textId="77421295" w:rsidR="001F3E92" w:rsidRDefault="001F3E92" w:rsidP="001F3E92"><w:pPr><w:jc w:val="center"/><w:rPr><w:b/><w:bCs/><w:sz w:val="28"/><w:szCs w:val="28"/></w:rPr></w:pPr><w:r w:rsidRPr="002C1B5F"><w:t>AWS CloudWatch</w:t></w:r></w:p></w:tc><w:tc><w:tcPr><w:tcW w:w="6662" w:type="dxa"/><w:vAlign w:val="center"/></w:tcPr><w:p w14:paraId="33103CB5" w14:textId="3CCFE513" w:rsidR="001F3E92" w:rsidRDefault="001F3E92" w:rsidP="001F3E92"><w:pPr><w:jc w:val="center"/><w:rPr><w:b/><w:bCs/><w:sz w:val="28"/><w:szCs w:val="28"/></w:rPr></w:pPr><w:r w:rsidRPr="002C1B5F"><w:t>Monitors Lambda activity and logs errors.</w:t></w:r></w:p></w:tc></w:tr><w:tr w:rsidR="001F3E92" w14:paraId="7E6D92A4" w14:textId="77777777" w:rsidTr="001F3E92"><w:tc><w:tcPr><w:tcW w:w="3545" w:type="dxa"/><w:vAlign w:val="center"/></w:tcPr><w:p w14:paraId="3F189766" w14:textId="4C9F9F5A" w:rsidR="001F3E92" w:rsidRPr="002C1B5F" w:rsidRDefault="001F3E92" w:rsidP="001F3E92"><w:pPr><w:jc w:val="center"/></w:pPr><w:r w:rsidRPr="002C1B5F"><w:t>AWS IAM</w:t></w:r></w:p></w:tc><w:tc><w:tcPr><w:tcW w:w="6662" w:type="dxa"/><w:vAlign w:val="center"/></w:tcPr><w:p w14:paraId="2D750C82" w14:textId="22B1309D" w:rsidR="001F3E92" w:rsidRPr="002C1B5F" w:rsidRDefault="001F3E92" w:rsidP="001F3E92"><w:pPr><w:jc w:val="center"/></w:pPr><w:r w:rsidRPr="002C1B5F"><w:t>Manages roles and policies to secure AWS service access.</w:t></w:r></w:p></w:tc></w:tr></w:tbl><w:p w14:paraId="61B34B74" w14:textId="77777777" w:rsidR="002C1B5F" w:rsidRPr="002C1B5F" w:rsidRDefault="0031267B" w:rsidP="002C1B5F"><w:r><w:pict w14:anchorId="236CF75B"><v:rect id="_x0000_i1028" style="width:0;height:1.5pt" o:hralign="center" o:hrstd="t" o:hr="t" fillcolor="#a0a0a0" stroked="f"/></w:pict></w:r></w:p><w:p w14:paraId="633D3C8F" w14:textId="77777777" w:rsidR="002864DC" w:rsidRDefault="002864DC" w:rsidP="001F3E92"><w:pPr><w:jc w:val="center"/><w:rPr><w:b/><w:bCs/><w:sz w:val="28"/><w:szCs w:val="28"/><w:highlight w:val="yellow"/></w:rPr></w:pPr></w:p><w:p w14:paraId="757CD087" w14:textId="77777777" w:rsidR="002864DC" w:rsidRDefault="002864DC" w:rsidP="001F3E92"><w:pPr><w:jc w:val="center"/><w:rPr><w:b/><w:bCs/><w:sz w:val="28"/><w:szCs w:val="28"/><w:highlight w:val="yellow"/></w:rPr></w:pPr></w:p><w:p w14:paraId="065F86E2" w14:textId="1D5EBE5F" w:rsidR="002864DC" w:rsidRPr="002864DC" w:rsidRDefault="002C1B5F" w:rsidP="002864DC"><w:pPr><w:jc w:val="center"/><w:rPr><w:b/><w:bCs/><w:sz w:val="28"/><w:szCs w:val="28"/></w:rPr></w:pPr><w:r w:rsidRPr="002C1B5F"><w:rPr><w:b/><w:bCs/><w:sz w:val="28"/><w:szCs w:val="28"/><w:highlight w:val="yellow"/></w:rPr><w:t>Project Implementation Detail</w:t></w:r><w:r w:rsidR="002864DC" w:rsidRPr="002864DC"><w:rPr><w:b/><w:bCs/><w:sz w:val="28"/><w:szCs w:val="28"/><w:highlight w:val="yellow"/></w:rPr><w:t>s</w:t></w:r></w:p><w:p w14:paraId="36EDB29C" w14:textId="230EB5C2" w:rsidR="002864DC" w:rsidRPr="00BB2E34" w:rsidRDefault="002C1B5F" w:rsidP="002864DC"><w:pPr><w:rPr><w:bCs/><w:color w:val="156082" w:themeColor="accent1"/><w:sz w:val="28"/><w:szCs w:val="28"/><w14:shadow w14:blurRad="38100" w14:dist="25400" w14:dir="5400000" w14:sx="100000" w14:sy="100000" w14:kx="0" w14:ky="0" w14:algn="ctr"><w14:srgbClr w14:val="6E747A"><w14:alpha w14:val="57000"/></w14:srgbClr></w14:shadow><w14:textOutline w14:w="0" w14:cap="flat" w14:cmpd="sng" w14:algn="ctr"><w14:noFill/><w14:prstDash w14:val="solid"/><w14:round/></w14:textOutline></w:rPr></w:pPr><w:r w:rsidRPr="002C1B5F"><w:rPr><w:bCs/><w:color w:val="156082" w:themeColor="accent1"/><w:sz w:val="28"/><w:szCs w:val="28"/><w14:shadow w14:blurRad="38100" w14:dist="25400" w14:dir="5400000" w14:sx="100000" w14:sy="100000" w14:kx="0" w14:ky="0" w14:algn="ctr"><w14:srgbClr w14:val="6E747A"><w14:alpha w14:val="57000"/></w14:srgbClr></w14:shadow><w14:textOutline w14:w="0" w14:cap="flat" w14:cmpd="sng" w14:algn="ctr"><w14:noFill/><w14:prstDash w14:val="solid"/><w14:round/></w14:textOutline></w:rPr><w:lastRenderedPageBreak/><w:t>Step 1: S3 Bucket Setup</w:t></w:r></w:p><w:p w14:paraId="05BDB1F0" w14:textId="3FD058DB" w:rsidR="002C1B5F" w:rsidRPr="002C1B5F" w:rsidRDefault="002C1B5F" w:rsidP="002864DC"><w:pPr><w:rPr><w:bCs/><w:color w:val="156082" w:themeColor="accent1"/><w14:shadow w14:blurRad="38100" w14:dist="25400" w14:dir="5400000" w14:sx="100000" w14:sy="100000" w14:kx="0" w14:ky="0" w14:algn="ctr"><w14:srgbClr w14:val="6E747A"><w14:alpha w14:val="57000"/></w14:srgbClr></w14:shadow><w14:textOutline w14:w="0" w14:cap="flat" w14:cmpd="sng" w14:algn="ctr"><w14:noFill/><w14:prstDash w14:val="solid"/><w14:round/></w14:textOutline></w:rPr></w:pPr><w:r w:rsidRPr="002C1B5F"><w:t>Created an S3 bucket</w:t></w:r><w:r w:rsidR="009A4973"><w:t xml:space="preserve"> “</w:t></w:r><w:r w:rsidR="009A4973" w:rsidRPr="009A4973"><w:rPr><w:b/><w:bCs/></w:rPr><w:t>my-data-pipeline-bucket-for-automated-file-upload</w:t></w:r><w:r w:rsidR="009A4973"><w:rPr><w:b/><w:bCs/></w:rPr><w:t>”</w:t></w:r><w:r w:rsidRPr="002C1B5F"><w:t xml:space="preserve"> to store uploaded CSV files.</w:t></w:r></w:p><w:p w14:paraId="595FE8AD" w14:textId="77777777" w:rsidR="002C1B5F" w:rsidRDefault="002C1B5F" w:rsidP="002C1B5F"><w:pPr><w:numPr><w:ilvl w:val="0"/><w:numId w:val="2"/></w:numPr></w:pPr><w:r w:rsidRPr="002C1B5F"><w:t>Enabled event notifications to trigger Lambda functions on object creation.</w:t></w:r></w:p><w:p w14:paraId="20E35995" w14:textId="01C0FED2" w:rsidR="006A6925" w:rsidRPr="002C1B5F" w:rsidRDefault="006A6925" w:rsidP="006A6925"><w:r w:rsidRPr="006A6925"><w:rPr><w:noProof/></w:rPr><w:drawing><wp:inline distT="0" distB="0" distL="0" distR="0" wp14:anchorId="63FC6553" wp14:editId="6B0A033C"><wp:extent cx="5731510" cy="1914525"/><wp:effectExtent l="0" t="0" r="2540" b="9525"/><wp:docPr id="1494545527" name="Picture 1"/><wp:cNvGraphicFramePr><a:graphicFrameLocks xmlns:a="http://schemas.openxmlformats.org/drawingml/2006/main" noChangeAspect="1"/></wp:cNvGraphicFramePr><a:graphic xmlns:a="http://schemas.openxmlformats.org/drawingml/2006/main"><a:graphicData uri="http://schemas.openxmlformats.org/drawingml/2006/picture"><pic:pic xmlns:pic="http://schemas.openxmlformats.org/drawingml/2006/picture"><pic:nvPicPr><pic:cNvPr id="1494545527" name=""/><pic:cNvPicPr/></pic:nvPicPr><pic:blipFill><a:blip r:embed="rId7"/><a:stretch><a:fillRect/></a:stretch></pic:blipFill><pic:spPr><a:xfrm><a:off x="0" y="0"/><a:ext cx="5731510" cy="1914525"/></a:xfrm><a:prstGeom prst="rect"><a:avLst/></a:prstGeom></pic:spPr></pic:pic></a:graphicData></a:graphic></wp:inline></w:drawing></w:r></w:p><w:p w14:paraId="4F6E204B" w14:textId="77777777" w:rsidR="002C1B5F" w:rsidRPr="002C1B5F" w:rsidRDefault="0031267B" w:rsidP="002C1B5F"><w:r><w:pict w14:anchorId="265A10DD"><v:rect id="_x0000_i1029" style="width:0;height:1.5pt" o:hralign="center" o:hrstd="t" o:hr="t" fillcolor="#a0a0a0" stroked="f"/></w:pict></w:r></w:p><w:p w14:paraId="4ED9C938" w14:textId="77777777" w:rsidR="002C1B5F" w:rsidRPr="002C1B5F" w:rsidRDefault="002C1B5F" w:rsidP="002C1B5F"><w:pPr><w:rPr><w:bCs/><w:color w:val="156082" w:themeColor="accent1"/><w:sz w:val="28"/><w:szCs w:val="28"/><w14:shadow w14:blurRad="38100" w14:dist="25400" w14:dir="5400000" w14:sx="100000" w14:sy="100000" w14:kx="0" w14:ky="0" w14:algn="ctr"><w14:srgbClr w14:val="6E747A"><w14:alpha w14:val="57000"/></w14:srgbClr></w14:shadow><w14:textOutline w14:w="0" w14:cap="flat" w14:cmpd="sng" w14:algn="ctr"><w14:noFill/><w14:prstDash w14:val="solid"/><w14:round/></w14:textOutline></w:rPr></w:pPr><w:r w:rsidRPr="002C1B5F"><w:rPr><w:bCs/><w:color w:val="156082" w:themeColor="accent1"/><w:sz w:val="28"/><w:szCs w:val="28"/><w14:shadow w14:blurRad="38100" w14:dist="25400" w14:dir="5400000" w14:sx="100000" w14:sy="100000" w14:kx="0" w14:ky="0" w14:algn="ctr"><w14:srgbClr w14:val="6E747A"><w14:alpha w14:val="57000"/></w14:srgbClr></w14:shadow><w14:textOutline w14:w="0" w14:cap="flat" w14:cmpd="sng" w14:algn="ctr"><w14:noFill/><w14:prstDash w14:val="solid"/><w14:round/></w14:textOutline></w:rPr><w:t>Step 2: Lambda Function</w:t></w:r></w:p><w:p w14:paraId="1409395F" w14:textId="77777777" w:rsidR="002C1B5F" w:rsidRPr="002C1B5F" w:rsidRDefault="002C1B5F" w:rsidP="002C1B5F"><w:pPr><w:numPr><w:ilvl w:val="0"/><w:numId w:val="3"/></w:numPr></w:pPr><w:r w:rsidRPr="002C1B5F"><w:t>Developed a Python Lambda function to process CSV files.</w:t></w:r></w:p><w:p w14:paraId="40EAA4B0" w14:textId="77777777" w:rsidR="002C1B5F" w:rsidRDefault="002C1B5F" w:rsidP="002C1B5F"><w:pPr><w:numPr><w:ilvl w:val="0"/><w:numId w:val="3"/></w:numPr></w:pPr><w:r w:rsidRPr="002C1B5F"><w:t>Configured Lambda environment variables: DB_HOST, DB_NAME, DB_USER, DB_PASSWORD, SNS_TOPIC_ARN.</w:t></w:r></w:p><w:p w14:paraId="39D09D8B" w14:textId="6B78D9C2" w:rsidR="002864DC" w:rsidRPr="002C1B5F" w:rsidRDefault="002864DC" w:rsidP="002864DC"><w:pPr><w:ind w:left="360"/></w:pPr><w:r w:rsidRPr="002864DC"><w:rPr><w:noProof/></w:rPr><w:drawing><wp:inline distT="0" distB="0" distL="0" distR="0" wp14:anchorId="1646E5BC" wp14:editId="61A644E4"><wp:extent cx="5731510" cy="2577465"/><wp:effectExtent l="0" t="0" r="2540" b="0"/><wp:docPr id="1112141882" name="Picture 1"/><wp:cNvGraphicFramePr><a:graphicFrameLocks xmlns:a="http://schemas.openxmlformats.org/drawingml/2006/main" noChangeAspect="1"/></wp:cNvGraphicFramePr><a:graphic xmlns:a="http://schemas.openxmlformats.org/drawingml/2006/main"><a:graphicData uri="http://schemas.openxmlformats.org/drawingml/2006/picture"><pic:pic xmlns:pic="http://schemas.openxmlformats.org/drawingml/2006/picture"><pic:nvPicPr><pic:cNvPr id="1112141882" name=""/><pic:cNvPicPr/></pic:nvPicPr><pic:blipFill><a:blip r:embed="rId8"/><a:stretch><a:fillRect/></a:stretch></pic:blipFill><pic:spPr><a:xfrm><a:off x="0" y="0"/><a:ext cx="5731510" cy="2577465"/></a:xfrm><a:prstGeom prst="rect"><a:avLst/></a:prstGeom></pic:spPr></pic:pic></a:graphicData></a:graphic></wp:inline></w:drawing></w:r></w:p><w:p w14:paraId="04BCD01A" w14:textId="77777777" w:rsidR="002C1B5F" w:rsidRPr="002C1B5F" w:rsidRDefault="002C1B5F" w:rsidP="002C1B5F"><w:pPr><w:numPr><w:ilvl w:val="0"/><w:numId w:val="3"/></w:numPr></w:pPr><w:r w:rsidRPr="002C1B5F"><w:t>Function logic:</w:t></w:r></w:p><w:p w14:paraId="5A8838F4" w14:textId="77777777" w:rsidR="002C1B5F" w:rsidRPr="002C1B5F" w:rsidRDefault="002C1B5F" w:rsidP="002C1B5F"><w:pPr><w:numPr><w:ilvl w:val="1"/><w:numId w:val="3"/></w:numPr></w:pPr><w:r w:rsidRPr="002C1B5F"><w:t>Retrieves the uploaded file from S3.</w:t></w:r></w:p><w:p w14:paraId="36FDDBBB" w14:textId="77777777" w:rsidR="002C1B5F" w:rsidRPr="002C1B5F" w:rsidRDefault="002C1B5F" w:rsidP="002C1B5F"><w:pPr><w:numPr><w:ilvl w:val="1"/><w:numId w:val="3"/></w:numPr></w:pPr><w:r w:rsidRPr="002C1B5F"><w:t>Reads and parses the CSV content.</w:t></w:r></w:p><w:p w14:paraId="43E36EC6" w14:textId="77777777" w:rsidR="002C1B5F" w:rsidRPr="002C1B5F" w:rsidRDefault="002C1B5F" w:rsidP="002C1B5F"><w:pPr><w:numPr><w:ilvl w:val="1"/><w:numId w:val="3"/></w:numPr></w:pPr><w:r w:rsidRPr="002C1B5F"><w:t xml:space="preserve">Connects to RDS and inserts data into the </w:t></w:r><w:proofErr w:type="gramStart"/><w:r w:rsidRPr="002C1B5F"><w:t>customers</w:t></w:r><w:proofErr w:type="gramEnd"/><w:r w:rsidRPr="002C1B5F"><w:t xml:space="preserve"> table.</w:t></w:r></w:p><w:p w14:paraId="071D739B" w14:textId="77777777" w:rsidR="002C1B5F" w:rsidRPr="002C1B5F" w:rsidRDefault="002C1B5F" w:rsidP="002C1B5F"><w:pPr><w:numPr><w:ilvl w:val="1"/><w:numId w:val="3"/></w:numPr></w:pPr><w:r w:rsidRPr="002C1B5F"><w:lastRenderedPageBreak/><w:t>Sends a success or failure notification via SNS.</w:t></w:r></w:p><w:p w14:paraId="0FE8B457" w14:textId="77777777" w:rsidR="002C1B5F" w:rsidRPr="002C1B5F" w:rsidRDefault="002C1B5F" w:rsidP="002C1B5F"><w:r w:rsidRPr="002C1B5F"><w:rPr><w:b/><w:bCs/></w:rPr><w:t>Lambda Function (Python):</w:t></w:r></w:p><w:p w14:paraId="5FB87F25" w14:textId="77777777" w:rsidR="002864DC" w:rsidRPr="002864DC" w:rsidRDefault="002864DC" w:rsidP="002864DC"><w:r w:rsidRPr="002864DC"><w:t>import boto3</w:t></w:r></w:p><w:p w14:paraId="43F291F2" w14:textId="77777777" w:rsidR="002864DC" w:rsidRPr="002864DC" w:rsidRDefault="002864DC" w:rsidP="002864DC"><w:r w:rsidRPr="002864DC"><w:t>import csv</w:t></w:r></w:p><w:p w14:paraId="4BD5D325" w14:textId="77777777" w:rsidR="002864DC" w:rsidRPr="002864DC" w:rsidRDefault="002864DC" w:rsidP="002864DC"><w:r w:rsidRPr="002864DC"><w:t xml:space="preserve">import </w:t></w:r><w:proofErr w:type="spellStart"/><w:r w:rsidRPr="002864DC"><w:t>os</w:t></w:r><w:proofErr w:type="spellEnd"/></w:p><w:p w14:paraId="6512114C" w14:textId="77777777" w:rsidR="002864DC" w:rsidRPr="002864DC" w:rsidRDefault="002864DC" w:rsidP="002864DC"><w:r w:rsidRPr="002864DC"><w:t xml:space="preserve">import </w:t></w:r><w:proofErr w:type="spellStart"/><w:r w:rsidRPr="002864DC"><w:t>pymysql</w:t></w:r><w:proofErr w:type="spellEnd"/></w:p><w:p w14:paraId="012E8F2B" w14:textId="77777777" w:rsidR="002864DC" w:rsidRPr="002864DC" w:rsidRDefault="002864DC" w:rsidP="002864DC"><w:r w:rsidRPr="002864DC"><w:t>import logging</w:t></w:r></w:p><w:p w14:paraId="72371014" w14:textId="77777777" w:rsidR="002864DC" w:rsidRPr="002864DC" w:rsidRDefault="002864DC" w:rsidP="002864DC"/><w:p w14:paraId="4570B698" w14:textId="77777777" w:rsidR="002864DC" w:rsidRPr="002864DC" w:rsidRDefault="002864DC" w:rsidP="002864DC"><w:r w:rsidRPr="002864DC"><w:t># Initialize clients</w:t></w:r></w:p><w:p w14:paraId="1019B6D2" w14:textId="77777777" w:rsidR="002864DC" w:rsidRPr="002864DC" w:rsidRDefault="002864DC" w:rsidP="002864DC"><w:r w:rsidRPr="002864DC"><w:t>s3_client = boto3.client('s3')</w:t></w:r></w:p><w:p w14:paraId="45874259" w14:textId="77777777" w:rsidR="002864DC" w:rsidRPr="002864DC" w:rsidRDefault="002864DC" w:rsidP="002864DC"><w:proofErr w:type="spellStart"/><w:r w:rsidRPr="002864DC"><w:t>sns_client</w:t></w:r><w:proofErr w:type="spellEnd"/><w:r w:rsidRPr="002864DC"><w:t xml:space="preserve"> = boto3.client('</w:t></w:r><w:proofErr w:type="spellStart"/><w:r w:rsidRPr="002864DC"><w:t>sns</w:t></w:r><w:proofErr w:type="spellEnd"/><w:r w:rsidRPr="002864DC"><w:t>')</w:t></w:r></w:p><w:p w14:paraId="710922AD" w14:textId="77777777" w:rsidR="002864DC" w:rsidRPr="002864DC" w:rsidRDefault="002864DC" w:rsidP="002864DC"><w:proofErr w:type="spellStart"/><w:r w:rsidRPr="002864DC"><w:t>sns_topic_arn</w:t></w:r><w:proofErr w:type="spellEnd"/><w:r w:rsidRPr="002864DC"><w:t xml:space="preserve"> = </w:t></w:r><w:proofErr w:type="spellStart"/><w:proofErr w:type="gramStart"/><w:r w:rsidRPr="002864DC"><w:t>os.environ</w:t></w:r><w:proofErr w:type="spellEnd"/><w:proofErr w:type="gramEnd"/><w:r w:rsidRPr="002864DC"><w:t>['SNS_TOPIC_ARN']</w:t></w:r></w:p><w:p w14:paraId="06843898" w14:textId="77777777" w:rsidR="002864DC" w:rsidRPr="002864DC" w:rsidRDefault="002864DC" w:rsidP="002864DC"/><w:p w14:paraId="197BC882" w14:textId="77777777" w:rsidR="002864DC" w:rsidRPr="002864DC" w:rsidRDefault="002864DC" w:rsidP="002864DC"><w:r w:rsidRPr="002864DC"><w:t># Setup logger</w:t></w:r></w:p><w:p w14:paraId="3CC7D9ED" w14:textId="77777777" w:rsidR="002864DC" w:rsidRPr="002864DC" w:rsidRDefault="002864DC" w:rsidP="002864DC"><w:r w:rsidRPr="002864DC"><w:t xml:space="preserve">logger = </w:t></w:r><w:proofErr w:type="spellStart"/><w:proofErr w:type="gramStart"/><w:r w:rsidRPr="002864DC"><w:t>logging.getLogger</w:t></w:r><w:proofErr w:type="spellEnd"/><w:proofErr w:type="gramEnd"/><w:r w:rsidRPr="002864DC"><w:t>()</w:t></w:r></w:p><w:p w14:paraId="5A002380" w14:textId="77777777" w:rsidR="002864DC" w:rsidRPr="002864DC" w:rsidRDefault="002864DC" w:rsidP="002864DC"><w:proofErr w:type="spellStart"/><w:proofErr w:type="gramStart"/><w:r w:rsidRPr="002864DC"><w:t>logger.setLevel</w:t></w:r><w:proofErr w:type="spellEnd"/><w:proofErr w:type="gramEnd"/><w:r w:rsidRPr="002864DC"><w:t>(logging.INFO)</w:t></w:r></w:p><w:p w14:paraId="525ECD80" w14:textId="77777777" w:rsidR="002864DC" w:rsidRPr="002864DC" w:rsidRDefault="002864DC" w:rsidP="002864DC"/><w:p w14:paraId="19FE85D6" w14:textId="77777777" w:rsidR="002864DC" w:rsidRPr="002864DC" w:rsidRDefault="002864DC" w:rsidP="002864DC"><w:r w:rsidRPr="002864DC"><w:t># Lambda handler</w:t></w:r></w:p><w:p w14:paraId="54613084" w14:textId="77777777" w:rsidR="002864DC" w:rsidRPr="002864DC" w:rsidRDefault="002864DC" w:rsidP="002864DC"><w:r w:rsidRPr="002864DC"><w:t xml:space="preserve">def </w:t></w:r><w:proofErr w:type="spellStart"/><w:r w:rsidRPr="002864DC"><w:t>lambda_</w:t></w:r><w:proofErr w:type="gramStart"/><w:r w:rsidRPr="002864DC"><w:t>handler</w:t></w:r><w:proofErr w:type="spellEnd"/><w:r w:rsidRPr="002864DC"><w:t>(</w:t></w:r><w:proofErr w:type="gramEnd"/><w:r w:rsidRPr="002864DC"><w:t>event, context):</w:t></w:r></w:p><w:p w14:paraId="2F8F26A0" w14:textId="77777777" w:rsidR="002864DC" w:rsidRPr="002864DC" w:rsidRDefault="002864DC" w:rsidP="002864DC"><w:r w:rsidRPr="002864DC"><w:t>    bucket = key = "Unknown"</w:t></w:r></w:p><w:p w14:paraId="21C98678" w14:textId="77777777" w:rsidR="002864DC" w:rsidRPr="002864DC" w:rsidRDefault="002864DC" w:rsidP="002864DC"><w:r w:rsidRPr="002864DC"><w:t>    try:</w:t></w:r></w:p><w:p w14:paraId="4B3861DD" w14:textId="77777777" w:rsidR="002864DC" w:rsidRPr="002864DC" w:rsidRDefault="002864DC" w:rsidP="002864DC"><w:r w:rsidRPr="002864DC"><w:t>        # Get bucket and key from S3 event</w:t></w:r></w:p><w:p w14:paraId="4D0F44EF" w14:textId="77777777" w:rsidR="002864DC" w:rsidRPr="002864DC" w:rsidRDefault="002864DC" w:rsidP="002864DC"><w:r w:rsidRPr="002864DC"><w:t>        bucket = event['Records'][</w:t></w:r><w:proofErr w:type="gramStart"/><w:r w:rsidRPr="002864DC"><w:t>0][</w:t></w:r><w:proofErr w:type="gramEnd"/><w:r w:rsidRPr="002864DC"><w:t>'s3</w:t></w:r><w:proofErr w:type="gramStart"/><w:r w:rsidRPr="002864DC"><w:t>'][</w:t></w:r><w:proofErr w:type="gramEnd"/><w:r w:rsidRPr="002864DC"><w:t>'bucket</w:t></w:r><w:proofErr w:type="gramStart"/><w:r w:rsidRPr="002864DC"><w:t>'][</w:t></w:r><w:proofErr w:type="gramEnd"/><w:r w:rsidRPr="002864DC"><w:t>'name']</w:t></w:r></w:p><w:p w14:paraId="5DD46302" w14:textId="77777777" w:rsidR="002864DC" w:rsidRPr="002864DC" w:rsidRDefault="002864DC" w:rsidP="002864DC"><w:r w:rsidRPr="002864DC"><w:t>        key = event['Records'][</w:t></w:r><w:proofErr w:type="gramStart"/><w:r w:rsidRPr="002864DC"><w:t>0][</w:t></w:r><w:proofErr w:type="gramEnd"/><w:r w:rsidRPr="002864DC"><w:t>'s3</w:t></w:r><w:proofErr w:type="gramStart"/><w:r w:rsidRPr="002864DC"><w:t>'][</w:t></w:r><w:proofErr w:type="gramEnd"/><w:r w:rsidRPr="002864DC"><w:t>'object</w:t></w:r><w:proofErr w:type="gramStart"/><w:r w:rsidRPr="002864DC"><w:t>'][</w:t></w:r><w:proofErr w:type="gramEnd"/><w:r w:rsidRPr="002864DC"><w:t>'key']</w:t></w:r></w:p><w:p w14:paraId="37E729EE" w14:textId="77777777" w:rsidR="002864DC" w:rsidRPr="002864DC" w:rsidRDefault="002864DC" w:rsidP="002864DC"><w:r w:rsidRPr="002864DC"><w:t xml:space="preserve">        </w:t></w:r><w:proofErr w:type="gramStart"/><w:r w:rsidRPr="002864DC"><w:t>logger.info(</w:t></w:r><w:proofErr w:type="spellStart"/><w:proofErr w:type="gramEnd"/><w:r w:rsidRPr="002864DC"><w:t>f"Processing</w:t></w:r><w:proofErr w:type="spellEnd"/><w:r w:rsidRPr="002864DC"><w:t xml:space="preserve"> file: {key} from bucket: {bucket}")</w:t></w:r></w:p><w:p w14:paraId="3A406002" w14:textId="77777777" w:rsidR="002864DC" w:rsidRPr="002864DC" w:rsidRDefault="002864DC" w:rsidP="002864DC"/><w:p w14:paraId="52B010AE" w14:textId="77777777" w:rsidR="002864DC" w:rsidRPr="002864DC" w:rsidRDefault="002864DC" w:rsidP="002864DC"><w:r w:rsidRPr="002864DC"><w:t>        # Download file from S3</w:t></w:r></w:p><w:p w14:paraId="477CC8E3" w14:textId="77777777" w:rsidR="002864DC" w:rsidRPr="002864DC" w:rsidRDefault="002864DC" w:rsidP="002864DC"><w:r w:rsidRPr="002864DC"><w:t>        response = s3_client.get_</w:t></w:r><w:proofErr w:type="gramStart"/><w:r w:rsidRPr="002864DC"><w:t>object(</w:t></w:r><w:proofErr w:type="gramEnd"/><w:r w:rsidRPr="002864DC"><w:t>Bucket=bucket, Key=key)</w:t></w:r></w:p><w:p w14:paraId="193398F7" w14:textId="77777777" w:rsidR="002864DC" w:rsidRPr="002864DC" w:rsidRDefault="002864DC" w:rsidP="002864DC"><w:r w:rsidRPr="002864DC"><w:lastRenderedPageBreak/><w:t>        content = response['Body'</w:t></w:r><w:proofErr w:type="gramStart"/><w:r w:rsidRPr="002864DC"><w:t>].read</w:t></w:r><w:proofErr w:type="gramEnd"/><w:r w:rsidRPr="002864DC"><w:t>(</w:t></w:r><w:proofErr w:type="gramStart"/><w:r w:rsidRPr="002864DC"><w:t>).decode</w:t></w:r><w:proofErr w:type="gramEnd"/><w:r w:rsidRPr="002864DC"><w:t>('utf-8'</w:t></w:r><w:proofErr w:type="gramStart"/><w:r w:rsidRPr="002864DC"><w:t>).</w:t></w:r><w:proofErr w:type="spellStart"/><w:r w:rsidRPr="002864DC"><w:t>splitlines</w:t></w:r><w:proofErr w:type="spellEnd"/><w:proofErr w:type="gramEnd"/><w:r w:rsidRPr="002864DC"><w:t>()</w:t></w:r></w:p><w:p w14:paraId="6B7FEFCE" w14:textId="77777777" w:rsidR="002864DC" w:rsidRPr="002864DC" w:rsidRDefault="002864DC" w:rsidP="002864DC"><w:r w:rsidRPr="002864DC"><w:t xml:space="preserve">        reader = </w:t></w:r><w:proofErr w:type="spellStart"/><w:proofErr w:type="gramStart"/><w:r w:rsidRPr="002864DC"><w:t>csv.DictReader</w:t></w:r><w:proofErr w:type="spellEnd"/><w:proofErr w:type="gramEnd"/><w:r w:rsidRPr="002864DC"><w:t>(content)</w:t></w:r></w:p><w:p w14:paraId="261F94E5" w14:textId="77777777" w:rsidR="002864DC" w:rsidRPr="002864DC" w:rsidRDefault="002864DC" w:rsidP="002864DC"/><w:p w14:paraId="249FCDC4" w14:textId="77777777" w:rsidR="002864DC" w:rsidRPr="002864DC" w:rsidRDefault="002864DC" w:rsidP="002864DC"><w:r w:rsidRPr="002864DC"><w:t>        # Connect to MariaDB (RDS)</w:t></w:r></w:p><w:p w14:paraId="21A59100" w14:textId="77777777" w:rsidR="002864DC" w:rsidRPr="002864DC" w:rsidRDefault="002864DC" w:rsidP="002864DC"><w:r w:rsidRPr="002864DC"><w:t xml:space="preserve">        conn = </w:t></w:r><w:proofErr w:type="spellStart"/><w:proofErr w:type="gramStart"/><w:r w:rsidRPr="002864DC"><w:t>pymysql.connect</w:t></w:r><w:proofErr w:type="spellEnd"/><w:proofErr w:type="gramEnd"/><w:r w:rsidRPr="002864DC"><w:t>(</w:t></w:r></w:p><w:p w14:paraId="67B87AB3" w14:textId="77777777" w:rsidR="002864DC" w:rsidRPr="002864DC" w:rsidRDefault="002864DC" w:rsidP="002864DC"><w:r w:rsidRPr="002864DC"><w:t xml:space="preserve">    host = </w:t></w:r><w:proofErr w:type="spellStart"/><w:proofErr w:type="gramStart"/><w:r w:rsidRPr="002864DC"><w:t>os.environ</w:t></w:r><w:proofErr w:type="spellEnd"/><w:proofErr w:type="gramEnd"/><w:r w:rsidRPr="002864DC"><w:t>['DB_HOST'],</w:t></w:r></w:p><w:p w14:paraId="2B480CBB" w14:textId="77777777" w:rsidR="002864DC" w:rsidRPr="002864DC" w:rsidRDefault="002864DC" w:rsidP="002864DC"><w:r w:rsidRPr="002864DC"><w:t xml:space="preserve">    user = </w:t></w:r><w:proofErr w:type="spellStart"/><w:proofErr w:type="gramStart"/><w:r w:rsidRPr="002864DC"><w:t>os.environ</w:t></w:r><w:proofErr w:type="spellEnd"/><w:proofErr w:type="gramEnd"/><w:r w:rsidRPr="002864DC"><w:t>['DB_USER'],</w:t></w:r></w:p><w:p w14:paraId="061D2466" w14:textId="77777777" w:rsidR="002864DC" w:rsidRPr="002864DC" w:rsidRDefault="002864DC" w:rsidP="002864DC"><w:r w:rsidRPr="002864DC"><w:t xml:space="preserve">    password = </w:t></w:r><w:proofErr w:type="spellStart"/><w:proofErr w:type="gramStart"/><w:r w:rsidRPr="002864DC"><w:t>os.environ</w:t></w:r><w:proofErr w:type="spellEnd"/><w:proofErr w:type="gramEnd"/><w:r w:rsidRPr="002864DC"><w:t>['DB_PASSWORD'],</w:t></w:r></w:p><w:p w14:paraId="270A14F4" w14:textId="77777777" w:rsidR="002864DC" w:rsidRPr="002864DC" w:rsidRDefault="002864DC" w:rsidP="002864DC"><w:r w:rsidRPr="002864DC"><w:t xml:space="preserve">    database = </w:t></w:r><w:proofErr w:type="spellStart"/><w:proofErr w:type="gramStart"/><w:r w:rsidRPr="002864DC"><w:t>os.environ</w:t></w:r><w:proofErr w:type="spellEnd"/><w:proofErr w:type="gramEnd"/><w:r w:rsidRPr="002864DC"><w:t>['DB_NAME'</w:t></w:r><w:proofErr w:type="gramStart"/><w:r w:rsidRPr="002864DC"><w:t xml:space="preserve">],   </w:t></w:r><w:proofErr w:type="gramEnd"/><w:r w:rsidRPr="002864DC"><w:t>    # ensure DB_NAME is correct: '</w:t></w:r><w:proofErr w:type="spellStart"/><w:r w:rsidRPr="002864DC"><w:t>customers_info</w:t></w:r><w:proofErr w:type="spellEnd"/><w:r w:rsidRPr="002864DC"><w:t>'</w:t></w:r></w:p><w:p w14:paraId="48D29B73" w14:textId="77777777" w:rsidR="002864DC" w:rsidRPr="002864DC" w:rsidRDefault="002864DC" w:rsidP="002864DC"><w:r w:rsidRPr="002864DC"><w:t xml:space="preserve">    port = </w:t></w:r><w:proofErr w:type="gramStart"/><w:r w:rsidRPr="002864DC"><w:t>int(</w:t></w:r><w:proofErr w:type="spellStart"/><w:r w:rsidRPr="002864DC"><w:t>os.environ.get</w:t></w:r><w:proofErr w:type="spellEnd"/><w:r w:rsidRPr="002864DC"><w:t>(</w:t></w:r><w:proofErr w:type="gramEnd"/><w:r w:rsidRPr="002864DC"><w:t>'DB_PORT', 3306))</w:t></w:r></w:p><w:p w14:paraId="52A25734" w14:textId="77777777" w:rsidR="002864DC" w:rsidRPr="002864DC" w:rsidRDefault="002864DC" w:rsidP="002864DC"><w:r w:rsidRPr="002864DC"><w:t>        )</w:t></w:r></w:p><w:p w14:paraId="38F84A38" w14:textId="77777777" w:rsidR="002864DC" w:rsidRPr="002864DC" w:rsidRDefault="002864DC" w:rsidP="002864DC"><w:r w:rsidRPr="002864DC"><w:t xml:space="preserve">        cur = </w:t></w:r><w:proofErr w:type="spellStart"/><w:proofErr w:type="gramStart"/><w:r w:rsidRPr="002864DC"><w:t>conn.cursor</w:t></w:r><w:proofErr w:type="spellEnd"/><w:proofErr w:type="gramEnd"/><w:r w:rsidRPr="002864DC"><w:t>()</w:t></w:r></w:p><w:p w14:paraId="28442880" w14:textId="77777777" w:rsidR="002864DC" w:rsidRPr="002864DC" w:rsidRDefault="002864DC" w:rsidP="002864DC"><w:r w:rsidRPr="002864DC"><w:t xml:space="preserve">        </w:t></w:r><w:proofErr w:type="spellStart"/><w:r w:rsidRPr="002864DC"><w:t>inserted_rows</w:t></w:r><w:proofErr w:type="spellEnd"/><w:r w:rsidRPr="002864DC"><w:t xml:space="preserve"> = 0</w:t></w:r></w:p><w:p w14:paraId="59D28E64" w14:textId="77777777" w:rsidR="002864DC" w:rsidRPr="002864DC" w:rsidRDefault="002864DC" w:rsidP="002864DC"/><w:p w14:paraId="7DAD6EA3" w14:textId="77777777" w:rsidR="002864DC" w:rsidRPr="002864DC" w:rsidRDefault="002864DC" w:rsidP="002864DC"><w:r w:rsidRPr="002864DC"><w:t>        # Insert rows into RDS</w:t></w:r></w:p><w:p w14:paraId="017A5B08" w14:textId="77777777" w:rsidR="002864DC" w:rsidRPr="002864DC" w:rsidRDefault="002864DC" w:rsidP="002864DC"><w:r w:rsidRPr="002864DC"><w:t>        for row in reader:</w:t></w:r></w:p><w:p w14:paraId="4E02E01A" w14:textId="77777777" w:rsidR="002864DC" w:rsidRPr="002864DC" w:rsidRDefault="002864DC" w:rsidP="002864DC"><w:r w:rsidRPr="002864DC"><w:t>            try:</w:t></w:r></w:p><w:p w14:paraId="5F5C2700" w14:textId="77777777" w:rsidR="002864DC" w:rsidRPr="002864DC" w:rsidRDefault="002864DC" w:rsidP="002864DC"><w:r w:rsidRPr="002864DC"><w:t xml:space="preserve">                </w:t></w:r><w:proofErr w:type="spellStart"/><w:r w:rsidRPr="002864DC"><w:t>customer_id</w:t></w:r><w:proofErr w:type="spellEnd"/><w:r w:rsidRPr="002864DC"><w:t xml:space="preserve"> = int(row['id'])</w:t></w:r></w:p><w:p w14:paraId="6D512355" w14:textId="77777777" w:rsidR="002864DC" w:rsidRPr="002864DC" w:rsidRDefault="002864DC" w:rsidP="002864DC"><w:r w:rsidRPr="002864DC"><w:t>                name = row['name'</w:t></w:r><w:proofErr w:type="gramStart"/><w:r w:rsidRPr="002864DC"><w:t>].strip</w:t></w:r><w:proofErr w:type="gramEnd"/><w:r w:rsidRPr="002864DC"><w:t>()</w:t></w:r></w:p><w:p w14:paraId="5CC56924" w14:textId="77777777" w:rsidR="002864DC" w:rsidRPr="002864DC" w:rsidRDefault="002864DC" w:rsidP="002864DC"><w:r w:rsidRPr="002864DC"><w:t>                email = row['email'</w:t></w:r><w:proofErr w:type="gramStart"/><w:r w:rsidRPr="002864DC"><w:t>].strip</w:t></w:r><w:proofErr w:type="gramEnd"/><w:r w:rsidRPr="002864DC"><w:t>()</w:t></w:r></w:p><w:p w14:paraId="1C5F6E42" w14:textId="77777777" w:rsidR="002864DC" w:rsidRPr="002864DC" w:rsidRDefault="002864DC" w:rsidP="002864DC"/><w:p w14:paraId="1415AE33" w14:textId="77777777" w:rsidR="002864DC" w:rsidRPr="002864DC" w:rsidRDefault="002864DC" w:rsidP="002864DC"><w:r w:rsidRPr="002864DC"><w:t>                # Insert or update to avoid duplicate IDs</w:t></w:r></w:p><w:p w14:paraId="1EC8944D" w14:textId="77777777" w:rsidR="002864DC" w:rsidRPr="002864DC" w:rsidRDefault="002864DC" w:rsidP="002864DC"><w:r w:rsidRPr="002864DC"><w:t xml:space="preserve">                </w:t></w:r><w:proofErr w:type="spellStart"/><w:r w:rsidRPr="002864DC"><w:t>sql</w:t></w:r><w:proofErr w:type="spellEnd"/><w:r w:rsidRPr="002864DC"><w:t xml:space="preserve"> = """</w:t></w:r></w:p><w:p w14:paraId="0FEE032D" w14:textId="77777777" w:rsidR="002864DC" w:rsidRPr="002864DC" w:rsidRDefault="002864DC" w:rsidP="002864DC"><w:r w:rsidRPr="002864DC"><w:t>                INSERT INTO customers (id, name, email)</w:t></w:r></w:p><w:p w14:paraId="38FC877A" w14:textId="77777777" w:rsidR="002864DC" w:rsidRPr="002864DC" w:rsidRDefault="002864DC" w:rsidP="002864DC"><w:r w:rsidRPr="002864DC"><w:t>                VALUES (%s, %s, %s)</w:t></w:r></w:p><w:p w14:paraId="4AE61AA7" w14:textId="77777777" w:rsidR="002864DC" w:rsidRPr="002864DC" w:rsidRDefault="002864DC" w:rsidP="002864DC"><w:r w:rsidRPr="002864DC"><w:t>                ON DUPLICATE KEY UPDATE</w:t></w:r></w:p><w:p w14:paraId="78994F82" w14:textId="77777777" w:rsidR="002864DC" w:rsidRPr="002864DC" w:rsidRDefault="002864DC" w:rsidP="002864DC"><w:r w:rsidRPr="002864DC"><w:t xml:space="preserve">                    name = </w:t></w:r><w:proofErr w:type="gramStart"/><w:r w:rsidRPr="002864DC"><w:t>VALUES(</w:t></w:r><w:proofErr w:type="gramEnd"/><w:r w:rsidRPr="002864DC"><w:t>name),</w:t></w:r></w:p><w:p w14:paraId="2C8C1C13" w14:textId="77777777" w:rsidR="002864DC" w:rsidRPr="002864DC" w:rsidRDefault="002864DC" w:rsidP="002864DC"><w:r w:rsidRPr="002864DC"><w:t xml:space="preserve">                    email = </w:t></w:r><w:proofErr w:type="gramStart"/><w:r w:rsidRPr="002864DC"><w:t>VALUES(</w:t></w:r><w:proofErr w:type="gramEnd"/><w:r w:rsidRPr="002864DC"><w:t>email</w:t></w:r><w:proofErr w:type="gramStart"/><w:r w:rsidRPr="002864DC"><w:t>);</w:t></w:r><w:proofErr w:type="gramEnd"/></w:p><w:p w14:paraId="161DC378" w14:textId="77777777" w:rsidR="002864DC" w:rsidRPr="002864DC" w:rsidRDefault="002864DC" w:rsidP="002864DC"><w:r w:rsidRPr="002864DC"><w:lastRenderedPageBreak/><w:t>                """</w:t></w:r></w:p><w:p w14:paraId="0EE09FC6" w14:textId="77777777" w:rsidR="002864DC" w:rsidRPr="002864DC" w:rsidRDefault="002864DC" w:rsidP="002864DC"><w:r w:rsidRPr="002864DC"><w:t xml:space="preserve">                </w:t></w:r><w:proofErr w:type="spellStart"/><w:proofErr w:type="gramStart"/><w:r w:rsidRPr="002864DC"><w:t>cur.execute</w:t></w:r><w:proofErr w:type="spellEnd"/><w:proofErr w:type="gramEnd"/><w:r w:rsidRPr="002864DC"><w:t>(</w:t></w:r><w:proofErr w:type="spellStart"/><w:r w:rsidRPr="002864DC"><w:t>sql</w:t></w:r><w:proofErr w:type="spellEnd"/><w:r w:rsidRPr="002864DC"><w:t>, (</w:t></w:r><w:proofErr w:type="spellStart"/><w:r w:rsidRPr="002864DC"><w:t>customer_id</w:t></w:r><w:proofErr w:type="spellEnd"/><w:r w:rsidRPr="002864DC"><w:t>, name, email))</w:t></w:r></w:p><w:p w14:paraId="5A5E25DA" w14:textId="77777777" w:rsidR="002864DC" w:rsidRPr="002864DC" w:rsidRDefault="002864DC" w:rsidP="002864DC"><w:r w:rsidRPr="002864DC"><w:t xml:space="preserve">                </w:t></w:r><w:proofErr w:type="spellStart"/><w:r w:rsidRPr="002864DC"><w:t>inserted_rows</w:t></w:r><w:proofErr w:type="spellEnd"/><w:r w:rsidRPr="002864DC"><w:t xml:space="preserve"> += 1</w:t></w:r></w:p><w:p w14:paraId="68DEFB80" w14:textId="77777777" w:rsidR="002864DC" w:rsidRPr="002864DC" w:rsidRDefault="002864DC" w:rsidP="002864DC"/><w:p w14:paraId="4D635F80" w14:textId="77777777" w:rsidR="002864DC" w:rsidRPr="002864DC" w:rsidRDefault="002864DC" w:rsidP="002864DC"><w:r w:rsidRPr="002864DC"><w:t xml:space="preserve">            except Exception as </w:t></w:r><w:proofErr w:type="spellStart"/><w:r w:rsidRPr="002864DC"><w:t>row_error</w:t></w:r><w:proofErr w:type="spellEnd"/><w:r w:rsidRPr="002864DC"><w:t>:</w:t></w:r></w:p><w:p w14:paraId="785390F5" w14:textId="77777777" w:rsidR="002864DC" w:rsidRPr="002864DC" w:rsidRDefault="002864DC" w:rsidP="002864DC"><w:r w:rsidRPr="002864DC"><w:t xml:space="preserve">                </w:t></w:r><w:proofErr w:type="spellStart"/><w:proofErr w:type="gramStart"/><w:r w:rsidRPr="002864DC"><w:t>logger.warning</w:t></w:r><w:proofErr w:type="spellEnd"/><w:proofErr w:type="gramEnd"/><w:r w:rsidRPr="002864DC"><w:t>(</w:t></w:r><w:proofErr w:type="spellStart"/><w:r w:rsidRPr="002864DC"><w:t>f"Skipping</w:t></w:r><w:proofErr w:type="spellEnd"/><w:r w:rsidRPr="002864DC"><w:t xml:space="preserve"> row {row} due to error: {</w:t></w:r><w:proofErr w:type="spellStart"/><w:r w:rsidRPr="002864DC"><w:t>row_error</w:t></w:r><w:proofErr w:type="spellEnd"/><w:r w:rsidRPr="002864DC"><w:t>}")</w:t></w:r></w:p><w:p w14:paraId="38ECF094" w14:textId="77777777" w:rsidR="002864DC" w:rsidRPr="002864DC" w:rsidRDefault="002864DC" w:rsidP="002864DC"/><w:p w14:paraId="74D6350E" w14:textId="77777777" w:rsidR="002864DC" w:rsidRPr="002864DC" w:rsidRDefault="002864DC" w:rsidP="002864DC"><w:r w:rsidRPr="002864DC"><w:t xml:space="preserve">        </w:t></w:r><w:proofErr w:type="spellStart"/><w:proofErr w:type="gramStart"/><w:r w:rsidRPr="002864DC"><w:t>conn.commit</w:t></w:r><w:proofErr w:type="spellEnd"/><w:proofErr w:type="gramEnd"/><w:r w:rsidRPr="002864DC"><w:t>()</w:t></w:r></w:p><w:p w14:paraId="58BE4B60" w14:textId="77777777" w:rsidR="002864DC" w:rsidRPr="002864DC" w:rsidRDefault="002864DC" w:rsidP="002864DC"><w:r w:rsidRPr="002864DC"><w:t xml:space="preserve">        </w:t></w:r><w:proofErr w:type="spellStart"/><w:proofErr w:type="gramStart"/><w:r w:rsidRPr="002864DC"><w:t>cur.close</w:t></w:r><w:proofErr w:type="spellEnd"/><w:proofErr w:type="gramEnd"/><w:r w:rsidRPr="002864DC"><w:t>()</w:t></w:r></w:p><w:p w14:paraId="175E944B" w14:textId="77777777" w:rsidR="002864DC" w:rsidRPr="002864DC" w:rsidRDefault="002864DC" w:rsidP="002864DC"><w:r w:rsidRPr="002864DC"><w:t xml:space="preserve">        </w:t></w:r><w:proofErr w:type="spellStart"/><w:proofErr w:type="gramStart"/><w:r w:rsidRPr="002864DC"><w:t>conn.close</w:t></w:r><w:proofErr w:type="spellEnd"/><w:proofErr w:type="gramEnd"/><w:r w:rsidRPr="002864DC"><w:t>()</w:t></w:r></w:p><w:p w14:paraId="226BC2BC" w14:textId="77777777" w:rsidR="002864DC" w:rsidRPr="002864DC" w:rsidRDefault="002864DC" w:rsidP="002864DC"><w:r w:rsidRPr="002864DC"><w:t xml:space="preserve">        </w:t></w:r><w:proofErr w:type="gramStart"/><w:r w:rsidRPr="002864DC"><w:t>logger.info(</w:t></w:r><w:proofErr w:type="spellStart"/><w:proofErr w:type="gramEnd"/><w:r w:rsidRPr="002864DC"><w:t>f"Inserted</w:t></w:r><w:proofErr w:type="spellEnd"/><w:r w:rsidRPr="002864DC"><w:t>/Updated {</w:t></w:r><w:proofErr w:type="spellStart"/><w:r w:rsidRPr="002864DC"><w:t>inserted_rows</w:t></w:r><w:proofErr w:type="spellEnd"/><w:r w:rsidRPr="002864DC"><w:t>} rows successfully.")</w:t></w:r></w:p><w:p w14:paraId="1B1A76B3" w14:textId="77777777" w:rsidR="002864DC" w:rsidRPr="002864DC" w:rsidRDefault="002864DC" w:rsidP="002864DC"/><w:p w14:paraId="614860AE" w14:textId="77777777" w:rsidR="002864DC" w:rsidRPr="002864DC" w:rsidRDefault="002864DC" w:rsidP="002864DC"><w:r w:rsidRPr="002864DC"><w:t>        # Send success notification</w:t></w:r></w:p><w:p w14:paraId="30B1E122" w14:textId="77777777" w:rsidR="002864DC" w:rsidRPr="002864DC" w:rsidRDefault="002864DC" w:rsidP="002864DC"><w:r w:rsidRPr="002864DC"><w:t xml:space="preserve">        </w:t></w:r><w:proofErr w:type="spellStart"/><w:r w:rsidRPr="002864DC"><w:t>sns_</w:t></w:r><w:proofErr w:type="gramStart"/><w:r w:rsidRPr="002864DC"><w:t>client.publish</w:t></w:r><w:proofErr w:type="spellEnd"/><w:proofErr w:type="gramEnd"/><w:r w:rsidRPr="002864DC"><w:t>(</w:t></w:r></w:p><w:p w14:paraId="33169ABC" w14:textId="77777777" w:rsidR="002864DC" w:rsidRPr="002864DC" w:rsidRDefault="002864DC" w:rsidP="002864DC"><w:r w:rsidRPr="002864DC"><w:t xml:space="preserve">            </w:t></w:r><w:proofErr w:type="spellStart"/><w:r w:rsidRPr="002864DC"><w:t>TopicArn</w:t></w:r><w:proofErr w:type="spellEnd"/><w:r w:rsidRPr="002864DC"><w:t>=</w:t></w:r><w:proofErr w:type="spellStart"/><w:r w:rsidRPr="002864DC"><w:t>sns_topic_arn</w:t></w:r><w:proofErr w:type="spellEnd"/><w:r w:rsidRPr="002864DC"><w:t>,</w:t></w:r></w:p><w:p w14:paraId="053AFFC8" w14:textId="77777777" w:rsidR="002864DC" w:rsidRPr="002864DC" w:rsidRDefault="002864DC" w:rsidP="002864DC"><w:r w:rsidRPr="002864DC"><w:t>            Subject="Data Insertion Success",</w:t></w:r></w:p><w:p w14:paraId="43735B32" w14:textId="77777777" w:rsidR="002864DC" w:rsidRPr="002864DC" w:rsidRDefault="002864DC" w:rsidP="002864DC"><w:r w:rsidRPr="002864DC"><w:t>            Message=</w:t></w:r><w:proofErr w:type="spellStart"/><w:r w:rsidRPr="002864DC"><w:t>f"File</w:t></w:r><w:proofErr w:type="spellEnd"/><w:r w:rsidRPr="002864DC"><w:t xml:space="preserve"> {key} processed successfully. Inserted/Updated {</w:t></w:r><w:proofErr w:type="spellStart"/><w:r w:rsidRPr="002864DC"><w:t>inserted_rows</w:t></w:r><w:proofErr w:type="spellEnd"/><w:r w:rsidRPr="002864DC"><w:t>} rows."</w:t></w:r></w:p><w:p w14:paraId="3B7E6834" w14:textId="77777777" w:rsidR="002864DC" w:rsidRPr="002864DC" w:rsidRDefault="002864DC" w:rsidP="002864DC"><w:r w:rsidRPr="002864DC"><w:t>        )</w:t></w:r></w:p><w:p w14:paraId="7B7060F6" w14:textId="77777777" w:rsidR="002864DC" w:rsidRPr="002864DC" w:rsidRDefault="002864DC" w:rsidP="002864DC"/><w:p w14:paraId="2144C7E9" w14:textId="77777777" w:rsidR="002864DC" w:rsidRPr="002864DC" w:rsidRDefault="002864DC" w:rsidP="002864DC"><w:r w:rsidRPr="002864DC"><w:t>    except Exception as e:</w:t></w:r></w:p><w:p w14:paraId="66B609F0" w14:textId="77777777" w:rsidR="002864DC" w:rsidRPr="002864DC" w:rsidRDefault="002864DC" w:rsidP="002864DC"><w:r w:rsidRPr="002864DC"><w:t xml:space="preserve">        </w:t></w:r><w:proofErr w:type="spellStart"/><w:proofErr w:type="gramStart"/><w:r w:rsidRPr="002864DC"><w:t>logger.error</w:t></w:r><w:proofErr w:type="spellEnd"/><w:proofErr w:type="gramEnd"/><w:r w:rsidRPr="002864DC"><w:t>(</w:t></w:r><w:proofErr w:type="spellStart"/><w:r w:rsidRPr="002864DC"><w:t>f"Failed</w:t></w:r><w:proofErr w:type="spellEnd"/><w:r w:rsidRPr="002864DC"><w:t xml:space="preserve"> to process file {key}: {e}")</w:t></w:r></w:p><w:p w14:paraId="70A82349" w14:textId="77777777" w:rsidR="002864DC" w:rsidRPr="002864DC" w:rsidRDefault="002864DC" w:rsidP="002864DC"><w:r w:rsidRPr="002864DC"><w:t xml:space="preserve">        </w:t></w:r><w:proofErr w:type="spellStart"/><w:r w:rsidRPr="002864DC"><w:t>sns_</w:t></w:r><w:proofErr w:type="gramStart"/><w:r w:rsidRPr="002864DC"><w:t>client.publish</w:t></w:r><w:proofErr w:type="spellEnd"/><w:proofErr w:type="gramEnd"/><w:r w:rsidRPr="002864DC"><w:t>(</w:t></w:r></w:p><w:p w14:paraId="7D5EA552" w14:textId="77777777" w:rsidR="002864DC" w:rsidRPr="002864DC" w:rsidRDefault="002864DC" w:rsidP="002864DC"><w:r w:rsidRPr="002864DC"><w:t xml:space="preserve">            </w:t></w:r><w:proofErr w:type="spellStart"/><w:r w:rsidRPr="002864DC"><w:t>TopicArn</w:t></w:r><w:proofErr w:type="spellEnd"/><w:r w:rsidRPr="002864DC"><w:t>=</w:t></w:r><w:proofErr w:type="spellStart"/><w:r w:rsidRPr="002864DC"><w:t>sns_topic_arn</w:t></w:r><w:proofErr w:type="spellEnd"/><w:r w:rsidRPr="002864DC"><w:t>,</w:t></w:r></w:p><w:p w14:paraId="32F93A18" w14:textId="77777777" w:rsidR="002864DC" w:rsidRPr="002864DC" w:rsidRDefault="002864DC" w:rsidP="002864DC"><w:r w:rsidRPr="002864DC"><w:t>            Subject="Data Insertion Failed",</w:t></w:r></w:p><w:p w14:paraId="1E367593" w14:textId="77777777" w:rsidR="002864DC" w:rsidRPr="002864DC" w:rsidRDefault="002864DC" w:rsidP="002864DC"><w:r w:rsidRPr="002864DC"><w:t>            Message=</w:t></w:r><w:proofErr w:type="spellStart"/><w:r w:rsidRPr="002864DC"><w:t>f"Error</w:t></w:r><w:proofErr w:type="spellEnd"/><w:r w:rsidRPr="002864DC"><w:t xml:space="preserve"> processing file {key}: {e}"</w:t></w:r></w:p><w:p w14:paraId="2A494D7D" w14:textId="77777777" w:rsidR="002864DC" w:rsidRPr="002864DC" w:rsidRDefault="002864DC" w:rsidP="002864DC"><w:r w:rsidRPr="002864DC"><w:t>        )</w:t></w:r></w:p><w:p w14:paraId="670BE1D6" w14:textId="723821BF" w:rsidR="002864DC" w:rsidRPr="002864DC" w:rsidRDefault="002864DC" w:rsidP="002864DC"><w:r w:rsidRPr="002864DC"><w:t>        raise e</w:t></w:r></w:p><w:p w14:paraId="4DAC04F3" w14:textId="40BD50CE" w:rsidR="002C1B5F" w:rsidRPr="002C1B5F" w:rsidRDefault="0031267B" w:rsidP="008C6091"><w:r><w:lastRenderedPageBreak/><w:pict w14:anchorId="6845A79A"><v:rect id="_x0000_i1030" style="width:0;height:1.5pt" o:hralign="center" o:hrstd="t" o:hr="t" fillcolor="#a0a0a0" stroked="f"/></w:pict></w:r></w:p><w:p w14:paraId="5B46CCCC" w14:textId="77777777" w:rsidR="002C1B5F" w:rsidRPr="002C1B5F" w:rsidRDefault="002C1B5F" w:rsidP="002C1B5F"><w:pPr><w:rPr><w:bCs/><w:color w:val="156082" w:themeColor="accent1"/><w:sz w:val="28"/><w:szCs w:val="28"/><w14:shadow w14:blurRad="38100" w14:dist="25400" w14:dir="5400000" w14:sx="100000" w14:sy="100000" w14:kx="0" w14:ky="0" w14:algn="ctr"><w14:srgbClr w14:val="6E747A"><w14:alpha w14:val="57000"/></w14:srgbClr></w14:shadow><w14:textOutline w14:w="0" w14:cap="flat" w14:cmpd="sng" w14:algn="ctr"><w14:noFill/><w14:prstDash w14:val="solid"/><w14:round/></w14:textOutline></w:rPr></w:pPr><w:r w:rsidRPr="002C1B5F"><w:rPr><w:bCs/><w:color w:val="156082" w:themeColor="accent1"/><w:sz w:val="28"/><w:szCs w:val="28"/><w14:shadow w14:blurRad="38100" w14:dist="25400" w14:dir="5400000" w14:sx="100000" w14:sy="100000" w14:kx="0" w14:ky="0" w14:algn="ctr"><w14:srgbClr w14:val="6E747A"><w14:alpha w14:val="57000"/></w14:srgbClr></w14:shadow><w14:textOutline w14:w="0" w14:cap="flat" w14:cmpd="sng" w14:algn="ctr"><w14:noFill/><w14:prstDash w14:val="solid"/><w14:round/></w14:textOutline></w:rPr><w:t>Step 3: RDS Configuration</w:t></w:r></w:p><w:p w14:paraId="3D3BDAC5" w14:textId="61530BF8" w:rsidR="00334780" w:rsidRPr="002C1B5F" w:rsidRDefault="002C1B5F" w:rsidP="00334780"><w:pPr><w:numPr><w:ilvl w:val="0"/><w:numId w:val="4"/></w:numPr></w:pPr><w:r w:rsidRPr="002C1B5F"><w:t>Created an RDS instance (</w:t></w:r><w:r w:rsidR="000578B2"><w:t>MariaDB</w:t></w:r><w:r w:rsidRPr="002C1B5F"><w:t>).</w:t></w:r></w:p><w:p w14:paraId="0E956C41" w14:textId="77777777" w:rsidR="002C1B5F" w:rsidRPr="002C1B5F" w:rsidRDefault="002C1B5F" w:rsidP="002C1B5F"><w:pPr><w:numPr><w:ilvl w:val="0"/><w:numId w:val="4"/></w:numPr></w:pPr><w:r w:rsidRPr="002C1B5F"><w:t>Defined the customers table schema:</w:t></w:r></w:p><w:p w14:paraId="1566BC27" w14:textId="77777777" w:rsidR="002C1B5F" w:rsidRPr="002C1B5F" w:rsidRDefault="002C1B5F" w:rsidP="002C1B5F"><w:r w:rsidRPr="002C1B5F"><w:t>CREATE TABLE customers (</w:t></w:r></w:p><w:p w14:paraId="214CE309" w14:textId="77777777" w:rsidR="002C1B5F" w:rsidRPr="002C1B5F" w:rsidRDefault="002C1B5F" w:rsidP="002C1B5F"><w:r w:rsidRPr="002C1B5F"><w:t xml:space="preserve">    id INT PRIMARY KEY,</w:t></w:r></w:p><w:p w14:paraId="1DAE92F5" w14:textId="77777777" w:rsidR="002C1B5F" w:rsidRPr="002C1B5F" w:rsidRDefault="002C1B5F" w:rsidP="002C1B5F"><w:r w:rsidRPr="002C1B5F"><w:t xml:space="preserve">    name </w:t></w:r><w:proofErr w:type="gramStart"/><w:r w:rsidRPr="002C1B5F"><w:t>VARCHAR(</w:t></w:r><w:proofErr w:type="gramEnd"/><w:r w:rsidRPr="002C1B5F"><w:t>100),</w:t></w:r></w:p><w:p w14:paraId="4D488DCE" w14:textId="77777777" w:rsidR="002C1B5F" w:rsidRPr="002C1B5F" w:rsidRDefault="002C1B5F" w:rsidP="002C1B5F"><w:r w:rsidRPr="002C1B5F"><w:t xml:space="preserve">    email </w:t></w:r><w:proofErr w:type="gramStart"/><w:r w:rsidRPr="002C1B5F"><w:t>VARCHAR(</w:t></w:r><w:proofErr w:type="gramEnd"/><w:r w:rsidRPr="002C1B5F"><w:t>100)</w:t></w:r></w:p><w:p w14:paraId="012E90D8" w14:textId="09C4606A" w:rsidR="00334780" w:rsidRDefault="002C1B5F" w:rsidP="002C1B5F"><w:r w:rsidRPr="002C1B5F"><w:t>);</w:t></w:r></w:p><w:p w14:paraId="7DA55E16" w14:textId="55D2F521" w:rsidR="002864DC" w:rsidRDefault="002864DC" w:rsidP="002C1B5F"><w:r w:rsidRPr="002864DC"><w:rPr><w:noProof/></w:rPr><w:drawing><wp:inline distT="0" distB="0" distL="0" distR="0" wp14:anchorId="1912D4A0" wp14:editId="5165A34B"><wp:extent cx="5731510" cy="2583180"/><wp:effectExtent l="0" t="0" r="2540" b="7620"/><wp:docPr id="435832456" name="Picture 1"/><wp:cNvGraphicFramePr><a:graphicFrameLocks xmlns:a="http://schemas.openxmlformats.org/drawingml/2006/main" noChangeAspect="1"/></wp:cNvGraphicFramePr><a:graphic xmlns:a="http://schemas.openxmlformats.org/drawingml/2006/main"><a:graphicData uri="http://schemas.openxmlformats.org/drawingml/2006/picture"><pic:pic xmlns:pic="http://schemas.openxmlformats.org/drawingml/2006/picture"><pic:nvPicPr><pic:cNvPr id="435832456" name=""/><pic:cNvPicPr/></pic:nvPicPr><pic:blipFill><a:blip r:embed="rId9"/><a:stretch><a:fillRect/></a:stretch></pic:blipFill><pic:spPr><a:xfrm><a:off x="0" y="0"/><a:ext cx="5731510" cy="2583180"/></a:xfrm><a:prstGeom prst="rect"><a:avLst/></a:prstGeom></pic:spPr></pic:pic></a:graphicData></a:graphic></wp:inline></w:drawing></w:r></w:p><w:p w14:paraId="3E0177EE" w14:textId="773C16FA" w:rsidR="00635273" w:rsidRPr="002C1B5F" w:rsidRDefault="00635273" w:rsidP="002C1B5F"/><w:p w14:paraId="69739F7D" w14:textId="77777777" w:rsidR="002C1B5F" w:rsidRPr="002C1B5F" w:rsidRDefault="0031267B" w:rsidP="002C1B5F"><w:r><w:pict w14:anchorId="533BBD6C"><v:rect id="_x0000_i1031" style="width:0;height:1.5pt" o:hralign="center" o:hrstd="t" o:hr="t" fillcolor="#a0a0a0" stroked="f"/></w:pict></w:r></w:p><w:p w14:paraId="13BA7E9E" w14:textId="77777777" w:rsidR="002C1B5F" w:rsidRPr="002C1B5F" w:rsidRDefault="002C1B5F" w:rsidP="002C1B5F"><w:pPr><w:rPr><w:b/><w:bCs/></w:rPr></w:pPr><w:r w:rsidRPr="002C1B5F"><w:rPr><w:b/><w:bCs/></w:rPr><w:t>Step 4: Local File Upload Script</w:t></w:r></w:p><w:p w14:paraId="74981EB4" w14:textId="77777777" w:rsidR="002C1B5F" w:rsidRPr="002C1B5F" w:rsidRDefault="002C1B5F" w:rsidP="002C1B5F"><w:pPr><w:numPr><w:ilvl w:val="0"/><w:numId w:val="5"/></w:numPr></w:pPr><w:r w:rsidRPr="002C1B5F"><w:t>Developed a Python script to upload CSV files to S3 from a local machine:</w:t></w:r></w:p><w:p w14:paraId="0ADEDF26" w14:textId="77777777" w:rsidR="002C1B5F" w:rsidRPr="002C1B5F" w:rsidRDefault="002C1B5F" w:rsidP="002C1B5F"><w:r w:rsidRPr="002C1B5F"><w:t>import boto3</w:t></w:r></w:p><w:p w14:paraId="23235CBE" w14:textId="77777777" w:rsidR="002C1B5F" w:rsidRPr="002C1B5F" w:rsidRDefault="002C1B5F" w:rsidP="002C1B5F"/><w:p w14:paraId="1EA9B7BF" w14:textId="77777777" w:rsidR="002C1B5F" w:rsidRPr="002C1B5F" w:rsidRDefault="002C1B5F" w:rsidP="002C1B5F"><w:r w:rsidRPr="002C1B5F"><w:t>s3 = boto3.client('s3')</w:t></w:r></w:p><w:p w14:paraId="6FFAE23E" w14:textId="60F9FFE9" w:rsidR="002C1B5F" w:rsidRPr="002C1B5F" w:rsidRDefault="002C1B5F" w:rsidP="002C1B5F"><w:proofErr w:type="spellStart"/><w:r w:rsidRPr="002C1B5F"><w:t>bucket_name</w:t></w:r><w:proofErr w:type="spellEnd"/><w:r w:rsidRPr="002C1B5F"><w:t xml:space="preserve"> = '</w:t></w:r><w:r w:rsidR="00BB2E34" w:rsidRPr="00BB2E34"><w:t>my-data-pipeline-bucket-for-automated-file-upload</w:t></w:r><w:r w:rsidRPr="002C1B5F"><w:t>'</w:t></w:r></w:p><w:p w14:paraId="06C645C9" w14:textId="77777777" w:rsidR="002C1B5F" w:rsidRPr="002C1B5F" w:rsidRDefault="002C1B5F" w:rsidP="002C1B5F"><w:proofErr w:type="spellStart"/><w:r w:rsidRPr="002C1B5F"><w:t>file_path</w:t></w:r><w:proofErr w:type="spellEnd"/><w:r w:rsidRPr="002C1B5F"><w:t xml:space="preserve"> = 'customers.csv'</w:t></w:r></w:p><w:p w14:paraId="7F6FDACD" w14:textId="77777777" w:rsidR="002C1B5F" w:rsidRPr="002C1B5F" w:rsidRDefault="002C1B5F" w:rsidP="002C1B5F"/><w:p w14:paraId="0129DFD1" w14:textId="77777777" w:rsidR="002C1B5F" w:rsidRPr="002C1B5F" w:rsidRDefault="002C1B5F" w:rsidP="002C1B5F"><w:r w:rsidRPr="002C1B5F"><w:lastRenderedPageBreak/><w:t>s</w:t></w:r><w:proofErr w:type="gramStart"/><w:r w:rsidRPr="002C1B5F"><w:t>3.upload</w:t></w:r><w:proofErr w:type="gramEnd"/><w:r w:rsidRPr="002C1B5F"><w:t>_</w:t></w:r><w:proofErr w:type="gramStart"/><w:r w:rsidRPr="002C1B5F"><w:t>file(</w:t></w:r><w:proofErr w:type="spellStart"/><w:proofErr w:type="gramEnd"/><w:r w:rsidRPr="002C1B5F"><w:t>file_path</w:t></w:r><w:proofErr w:type="spellEnd"/><w:r w:rsidRPr="002C1B5F"><w:t xml:space="preserve">, </w:t></w:r><w:proofErr w:type="spellStart"/><w:r w:rsidRPr="002C1B5F"><w:t>bucket_name</w:t></w:r><w:proofErr w:type="spellEnd"/><w:r w:rsidRPr="002C1B5F"><w:t>, 'uploads/customers.csv')</w:t></w:r></w:p><w:p w14:paraId="3E7BF36C" w14:textId="7ADE023E" w:rsidR="002C1B5F" w:rsidRPr="002C1B5F" w:rsidRDefault="002C1B5F" w:rsidP="002C1B5F"><w:proofErr w:type="gramStart"/><w:r w:rsidRPr="002C1B5F"><w:t>print(</w:t></w:r><w:proofErr w:type="gramEnd"/><w:r w:rsidRPr="002C1B5F"><w:t>"Upload successful.")</w:t></w:r><w:r w:rsidR="00F7639B" w:rsidRPr="00F7639B"><w:rPr><w:noProof/></w:rPr><w:t xml:space="preserve"> </w:t></w:r><w:r w:rsidR="00F7639B" w:rsidRPr="00F7639B"><w:rPr><w:noProof/></w:rPr><w:drawing><wp:inline distT="0" distB="0" distL="0" distR="0" wp14:anchorId="54439A77" wp14:editId="7D22B1F8"><wp:extent cx="5731510" cy="2943225"/><wp:effectExtent l="0" t="0" r="2540" b="9525"/><wp:docPr id="1115865889" name="Picture 1" descr="A screenshot of a computer&#xA;&#xA;AI-generated content may be incorrect."/><wp:cNvGraphicFramePr><a:graphicFrameLocks xmlns:a="http://schemas.openxmlformats.org/drawingml/2006/main" noChangeAspect="1"/></wp:cNvGraphicFramePr><a:graphic xmlns:a="http://schemas.openxmlformats.org/drawingml/2006/main"><a:graphicData uri="http://schemas.openxmlformats.org/drawingml/2006/picture"><pic:pic xmlns:pic="http://schemas.openxmlformats.org/drawingml/2006/picture"><pic:nvPicPr><pic:cNvPr id="1115865889" name="Picture 1" descr="A screenshot of a computer&#xA;&#xA;AI-generated content may be incorrect."/><pic:cNvPicPr/></pic:nvPicPr><pic:blipFill><a:blip r:embed="rId10"/><a:stretch><a:fillRect/></a:stretch></pic:blipFill><pic:spPr><a:xfrm><a:off x="0" y="0"/><a:ext cx="5731510" cy="2943225"/></a:xfrm><a:prstGeom prst="rect"><a:avLst/></a:prstGeom></pic:spPr></pic:pic></a:graphicData></a:graphic></wp:inline></w:drawing></w:r></w:p><w:p w14:paraId="34364D4E" w14:textId="77777777" w:rsidR="002C1B5F" w:rsidRPr="002C1B5F" w:rsidRDefault="0031267B" w:rsidP="002C1B5F"><w:r><w:pict w14:anchorId="35DEC974"><v:rect id="_x0000_i1032" style="width:0;height:1.5pt" o:hralign="center" o:hrstd="t" o:hr="t" fillcolor="#a0a0a0" stroked="f"/></w:pict></w:r></w:p><w:p w14:paraId="22406AD3" w14:textId="77777777" w:rsidR="002C1B5F" w:rsidRPr="002C1B5F" w:rsidRDefault="002C1B5F" w:rsidP="002C1B5F"><w:pPr><w:rPr><w:bCs/><w:color w:val="156082" w:themeColor="accent1"/><w:sz w:val="28"/><w:szCs w:val="28"/><w14:shadow w14:blurRad="38100" w14:dist="25400" w14:dir="5400000" w14:sx="100000" w14:sy="100000" w14:kx="0" w14:ky="0" w14:algn="ctr"><w14:srgbClr w14:val="6E747A"><w14:alpha w14:val="57000"/></w14:srgbClr></w14:shadow><w14:textOutline w14:w="0" w14:cap="flat" w14:cmpd="sng" w14:algn="ctr"><w14:noFill/><w14:prstDash w14:val="solid"/><w14:round/></w14:textOutline></w:rPr></w:pPr><w:r w:rsidRPr="002C1B5F"><w:rPr><w:bCs/><w:color w:val="156082" w:themeColor="accent1"/><w:sz w:val="28"/><w:szCs w:val="28"/><w14:shadow w14:blurRad="38100" w14:dist="25400" w14:dir="5400000" w14:sx="100000" w14:sy="100000" w14:kx="0" w14:ky="0" w14:algn="ctr"><w14:srgbClr w14:val="6E747A"><w14:alpha w14:val="57000"/></w14:srgbClr></w14:shadow><w14:textOutline w14:w="0" w14:cap="flat" w14:cmpd="sng" w14:algn="ctr"><w14:noFill/><w14:prstDash w14:val="solid"/><w14:round/></w14:textOutline></w:rPr><w:t>Step 5: IAM &amp; Networking</w:t></w:r></w:p><w:p w14:paraId="1C4EF10E" w14:textId="77777777" w:rsidR="002C1B5F" w:rsidRPr="002C1B5F" w:rsidRDefault="002C1B5F" w:rsidP="002C1B5F"><w:pPr><w:numPr><w:ilvl w:val="0"/><w:numId w:val="6"/></w:numPr></w:pPr><w:r w:rsidRPr="002C1B5F"><w:t>Created an IAM role for Lambda with the following permissions:</w:t></w:r></w:p><w:p w14:paraId="1B8255BE" w14:textId="77777777" w:rsidR="002C1B5F" w:rsidRPr="002C1B5F" w:rsidRDefault="002C1B5F" w:rsidP="002C1B5F"><w:pPr><w:numPr><w:ilvl w:val="1"/><w:numId w:val="6"/></w:numPr></w:pPr><w:r w:rsidRPr="002C1B5F"><w:t>AmazonS3ReadOnlyAccess</w:t></w:r></w:p><w:p w14:paraId="72202194" w14:textId="77777777" w:rsidR="002C1B5F" w:rsidRPr="002C1B5F" w:rsidRDefault="002C1B5F" w:rsidP="002C1B5F"><w:pPr><w:numPr><w:ilvl w:val="1"/><w:numId w:val="6"/></w:numPr></w:pPr><w:proofErr w:type="spellStart"/><w:r w:rsidRPr="002C1B5F"><w:t>AmazonRDSFullAccess</w:t></w:r><w:proofErr w:type="spellEnd"/></w:p><w:p w14:paraId="55B51683" w14:textId="77777777" w:rsidR="002C1B5F" w:rsidRPr="002C1B5F" w:rsidRDefault="002C1B5F" w:rsidP="002C1B5F"><w:pPr><w:numPr><w:ilvl w:val="1"/><w:numId w:val="6"/></w:numPr></w:pPr><w:proofErr w:type="spellStart"/><w:r w:rsidRPr="002C1B5F"><w:t>AmazonSNSFullAccess</w:t></w:r><w:proofErr w:type="spellEnd"/></w:p><w:p w14:paraId="1F2D8139" w14:textId="77777777" w:rsidR="002C1B5F" w:rsidRPr="002C1B5F" w:rsidRDefault="002C1B5F" w:rsidP="002C1B5F"><w:pPr><w:numPr><w:ilvl w:val="1"/><w:numId w:val="6"/></w:numPr></w:pPr><w:proofErr w:type="spellStart"/><w:r w:rsidRPr="002C1B5F"><w:t>AWSLambdaBasicExecutionRole</w:t></w:r><w:proofErr w:type="spellEnd"/></w:p><w:p w14:paraId="2FC3352F" w14:textId="77777777" w:rsidR="002C1B5F" w:rsidRPr="002C1B5F" w:rsidRDefault="002C1B5F" w:rsidP="002C1B5F"><w:pPr><w:numPr><w:ilvl w:val="0"/><w:numId w:val="6"/></w:numPr></w:pPr><w:r w:rsidRPr="002C1B5F"><w:t>Ensured Lambda can access RDS securely (VPC configuration if required).</w:t></w:r></w:p><w:p w14:paraId="6EDC1EDE" w14:textId="77777777" w:rsidR="002C1B5F" w:rsidRPr="002C1B5F" w:rsidRDefault="0031267B" w:rsidP="002C1B5F"><w:r><w:pict w14:anchorId="3EE32C3A"><v:rect id="_x0000_i1033" style="width:0;height:1.5pt" o:hralign="center" o:hrstd="t" o:hr="t" fillcolor="#a0a0a0" stroked="f"/></w:pict></w:r></w:p><w:p w14:paraId="0D991FD7" w14:textId="77777777" w:rsidR="002C1B5F" w:rsidRPr="002C1B5F" w:rsidRDefault="002C1B5F" w:rsidP="002C1B5F"><w:pPr><w:rPr><w:bCs/><w:color w:val="156082" w:themeColor="accent1"/><w:sz w:val="28"/><w:szCs w:val="28"/><w14:shadow w14:blurRad="38100" w14:dist="25400" w14:dir="5400000" w14:sx="100000" w14:sy="100000" w14:kx="0" w14:ky="0" w14:algn="ctr"><w14:srgbClr w14:val="6E747A"><w14:alpha w14:val="57000"/></w14:srgbClr></w14:shadow><w14:textOutline w14:w="0" w14:cap="flat" w14:cmpd="sng" w14:algn="ctr"><w14:noFill/><w14:prstDash w14:val="solid"/><w14:round/></w14:textOutline></w:rPr></w:pPr><w:r w:rsidRPr="002C1B5F"><w:rPr><w:bCs/><w:color w:val="156082" w:themeColor="accent1"/><w:sz w:val="28"/><w:szCs w:val="28"/><w14:shadow w14:blurRad="38100" w14:dist="25400" w14:dir="5400000" w14:sx="100000" w14:sy="100000" w14:kx="0" w14:ky="0" w14:algn="ctr"><w14:srgbClr w14:val="6E747A"><w14:alpha w14:val="57000"/></w14:srgbClr></w14:shadow><w14:textOutline w14:w="0" w14:cap="flat" w14:cmpd="sng" w14:algn="ctr"><w14:noFill/><w14:prstDash w14:val="solid"/><w14:round/></w14:textOutline></w:rPr><w:t>Step 6: CloudWatch Monitoring</w:t></w:r></w:p><w:p w14:paraId="466731E1" w14:textId="77777777" w:rsidR="002C1B5F" w:rsidRPr="002C1B5F" w:rsidRDefault="002C1B5F" w:rsidP="002C1B5F"><w:pPr><w:numPr><w:ilvl w:val="0"/><w:numId w:val="7"/></w:numPr></w:pPr><w:r w:rsidRPr="002C1B5F"><w:t>Enabled logging for Lambda invocations and errors.</w:t></w:r></w:p><w:p w14:paraId="7FF1561B" w14:textId="77777777" w:rsidR="002C1B5F" w:rsidRPr="002C1B5F" w:rsidRDefault="002C1B5F" w:rsidP="002C1B5F"><w:pPr><w:numPr><w:ilvl w:val="0"/><w:numId w:val="7"/></w:numPr></w:pPr><w:r w:rsidRPr="002C1B5F"><w:t>Created metric filters to detect failed inserts or errors.</w:t></w:r></w:p><w:p w14:paraId="6881540D" w14:textId="77777777" w:rsidR="002C1B5F" w:rsidRPr="002C1B5F" w:rsidRDefault="002C1B5F" w:rsidP="002C1B5F"><w:pPr><w:numPr><w:ilvl w:val="0"/><w:numId w:val="7"/></w:numPr></w:pPr><w:r w:rsidRPr="002C1B5F"><w:t>Configured alarms for high error rates to ensure pipeline reliability.</w:t></w:r></w:p><w:p w14:paraId="44825582" w14:textId="77777777" w:rsidR="002C1B5F" w:rsidRPr="002C1B5F" w:rsidRDefault="0031267B" w:rsidP="002C1B5F"><w:r><w:pict w14:anchorId="2C2472AE"><v:rect id="_x0000_i1034" style="width:0;height:1.5pt" o:hralign="center" o:hrstd="t" o:hr="t" fillcolor="#a0a0a0" stroked="f"/></w:pict></w:r></w:p><w:p w14:paraId="57172D73" w14:textId="77777777" w:rsidR="002C1B5F" w:rsidRPr="002C1B5F" w:rsidRDefault="002C1B5F" w:rsidP="002C1B5F"><w:pPr><w:rPr><w:bCs/><w:color w:val="156082" w:themeColor="accent1"/><w:sz w:val="28"/><w:szCs w:val="28"/><w14:shadow w14:blurRad="38100" w14:dist="25400" w14:dir="5400000" w14:sx="100000" w14:sy="100000" w14:kx="0" w14:ky="0" w14:algn="ctr"><w14:srgbClr w14:val="6E747A"><w14:alpha w14:val="57000"/></w14:srgbClr></w14:shadow><w14:textOutline w14:w="0" w14:cap="flat" w14:cmpd="sng" w14:algn="ctr"><w14:noFill/><w14:prstDash w14:val="solid"/><w14:round/></w14:textOutline></w:rPr></w:pPr><w:r w:rsidRPr="002C1B5F"><w:rPr><w:bCs/><w:color w:val="156082" w:themeColor="accent1"/><w:sz w:val="28"/><w:szCs w:val="28"/><w14:shadow w14:blurRad="38100" w14:dist="25400" w14:dir="5400000" w14:sx="100000" w14:sy="100000" w14:kx="0" w14:ky="0" w14:algn="ctr"><w14:srgbClr w14:val="6E747A"><w14:alpha w14:val="57000"/></w14:srgbClr></w14:shadow><w14:textOutline w14:w="0" w14:cap="flat" w14:cmpd="sng" w14:algn="ctr"><w14:noFill/><w14:prstDash w14:val="solid"/><w14:round/></w14:textOutline></w:rPr><w:t>Step 7: Testing and Validation</w:t></w:r></w:p><w:tbl><w:tblPr><w:tblW w:w="0" w:type="auto"/><w:tblCellSpacing w:w="15" w:type="dxa"/><w:tblCellMar><w:top w:w="15" w:type="dxa"/><w:left w:w="15" w:type="dxa"/><w:bottom w:w="15" w:type="dxa"/><w:right w:w="15" w:type="dxa"/></w:tblCellMar><w:tblLook w:val="04A0" w:firstRow="1" w:lastRow="0" w:firstColumn="1" w:lastColumn="0" w:noHBand="0" w:noVBand="1"/></w:tblPr><w:tblGrid><w:gridCol w:w="8945"/><w:gridCol w:w="81"/></w:tblGrid><w:tr w:rsidR="00BB2E34" w:rsidRPr="002C1B5F" w14:paraId="453335E7" w14:textId="77777777" w:rsidTr="00F7639B"><w:trPr><w:tblCellSpacing w:w="15" w:type="dxa"/></w:trPr><w:tc><w:tcPr><w:tcW w:w="8900" w:type="dxa"/><w:vAlign w:val="center"/></w:tcPr><w:tbl><w:tblPr><w:tblStyle w:val="TableGrid"/><w:tblW w:w="8594" w:type="dxa"/><w:tblLook w:val="04A0" w:firstRow="1" w:lastRow="0" w:firstColumn="1" w:lastColumn="0" w:noHBand="0" w:noVBand="1"/></w:tblPr><w:tblGrid><w:gridCol w:w="3491"/><w:gridCol w:w="5103"/></w:tblGrid><w:tr w:rsidR="00BB2E34" w14:paraId="0F88CB58" w14:textId="77777777" w:rsidTr="00BB2E34"><w:tc><w:tcPr><w:tcW w:w="3491" w:type="dxa"/><w:vAlign w:val="center"/></w:tcPr><w:p w14:paraId="48DD3A3F" w14:textId="6B8F1FB7" w:rsidR="00BB2E34" w:rsidRDefault="00BB2E34" w:rsidP="00BB2E34"><w:pPr><w:jc w:val="center"/></w:pPr><w:r w:rsidRPr="002C1B5F"><w:rPr><w:b/><w:bCs/></w:rPr><w:lastRenderedPageBreak/><w:t>Action</w:t></w:r></w:p></w:tc><w:tc><w:tcPr><w:tcW w:w="5103" w:type="dxa"/><w:vAlign w:val="center"/></w:tcPr><w:p w14:paraId="6A10548E" w14:textId="6CC09262" w:rsidR="00BB2E34" w:rsidRDefault="00BB2E34" w:rsidP="00BB2E34"><w:pPr><w:jc w:val="center"/></w:pPr><w:r w:rsidRPr="002C1B5F"><w:rPr><w:b/><w:bCs/></w:rPr><w:t>Expected Result</w:t></w:r></w:p></w:tc></w:tr><w:tr w:rsidR="00BB2E34" w14:paraId="5EC32554" w14:textId="77777777" w:rsidTr="00BB2E34"><w:tc><w:tcPr><w:tcW w:w="3491" w:type="dxa"/><w:vAlign w:val="center"/></w:tcPr><w:p w14:paraId="0DED96D6" w14:textId="1A44AC07" w:rsidR="00BB2E34" w:rsidRDefault="00BB2E34" w:rsidP="00BB2E34"><w:pPr><w:jc w:val="center"/></w:pPr><w:r w:rsidRPr="002C1B5F"><w:t>Upload CSV to S3</w:t></w:r></w:p></w:tc><w:tc><w:tcPr><w:tcW w:w="5103" w:type="dxa"/><w:vAlign w:val="center"/></w:tcPr><w:p w14:paraId="6EC03521" w14:textId="57885737" w:rsidR="00BB2E34" w:rsidRDefault="00BB2E34" w:rsidP="00BB2E34"><w:pPr><w:jc w:val="center"/></w:pPr><w:r w:rsidRPr="002C1B5F"><w:t>Lambda triggers automatically</w:t></w:r></w:p></w:tc></w:tr><w:tr w:rsidR="00BB2E34" w14:paraId="27C561FA" w14:textId="77777777" w:rsidTr="00BB2E34"><w:tc><w:tcPr><w:tcW w:w="3491" w:type="dxa"/><w:vAlign w:val="center"/></w:tcPr><w:p w14:paraId="7F7BE88B" w14:textId="2486CE8C" w:rsidR="00BB2E34" w:rsidRDefault="00BB2E34" w:rsidP="00BB2E34"><w:pPr><w:jc w:val="center"/></w:pPr><w:r w:rsidRPr="002C1B5F"><w:t>CSV contains new records</w:t></w:r></w:p></w:tc><w:tc><w:tcPr><w:tcW w:w="5103" w:type="dxa"/><w:vAlign w:val="center"/></w:tcPr><w:p w14:paraId="4F952551" w14:textId="62AE841C" w:rsidR="00BB2E34" w:rsidRDefault="00BB2E34" w:rsidP="00BB2E34"><w:pPr><w:jc w:val="center"/></w:pPr><w:r w:rsidRPr="002C1B5F"><w:t>Records inserted into RDS successfully</w:t></w:r></w:p></w:tc></w:tr><w:tr w:rsidR="00BB2E34" w14:paraId="505621AD" w14:textId="77777777" w:rsidTr="00BB2E34"><w:tc><w:tcPr><w:tcW w:w="3491" w:type="dxa"/><w:vAlign w:val="center"/></w:tcPr><w:p w14:paraId="5A4C8D95" w14:textId="5C0F094D" w:rsidR="00BB2E34" w:rsidRDefault="00BB2E34" w:rsidP="00BB2E34"><w:pPr><w:jc w:val="center"/></w:pPr><w:r w:rsidRPr="002C1B5F"><w:t>Lambda completes</w:t></w:r></w:p></w:tc><w:tc><w:tcPr><w:tcW w:w="5103" w:type="dxa"/><w:vAlign w:val="center"/></w:tcPr><w:p w14:paraId="45E07E32" w14:textId="47E4B4BA" w:rsidR="00BB2E34" w:rsidRDefault="00BB2E34" w:rsidP="00BB2E34"><w:pPr><w:jc w:val="center"/></w:pPr><w:r w:rsidRPr="002C1B5F"><w:t>SNS sends success notification</w:t></w:r></w:p></w:tc></w:tr><w:tr w:rsidR="00BB2E34" w14:paraId="17BAF38F" w14:textId="77777777" w:rsidTr="00BB2E34"><w:tc><w:tcPr><w:tcW w:w="3491" w:type="dxa"/><w:vAlign w:val="center"/></w:tcPr><w:p w14:paraId="1356B7B4" w14:textId="2BF610AC" w:rsidR="00BB2E34" w:rsidRDefault="00BB2E34" w:rsidP="00BB2E34"><w:pPr><w:jc w:val="center"/></w:pPr><w:r w:rsidRPr="002C1B5F"><w:t>Lambda fails</w:t></w:r></w:p></w:tc><w:tc><w:tcPr><w:tcW w:w="5103" w:type="dxa"/><w:vAlign w:val="center"/></w:tcPr><w:p w14:paraId="00D21D4E" w14:textId="19EA6CCE" w:rsidR="00BB2E34" w:rsidRDefault="00BB2E34" w:rsidP="00BB2E34"><w:pPr><w:jc w:val="center"/></w:pPr><w:r w:rsidRPr="002C1B5F"><w:t>SNS sends failure notification</w:t></w:r></w:p></w:tc></w:tr><w:tr w:rsidR="00BB2E34" w14:paraId="6FD3CA2B" w14:textId="77777777" w:rsidTr="00BB2E34"><w:tc><w:tcPr><w:tcW w:w="3491" w:type="dxa"/><w:vAlign w:val="center"/></w:tcPr><w:p w14:paraId="7A1E6D98" w14:textId="515CD7E7" w:rsidR="00BB2E34" w:rsidRDefault="00BB2E34" w:rsidP="00BB2E34"><w:pPr><w:jc w:val="center"/></w:pPr><w:r w:rsidRPr="002C1B5F"><w:t>Logs</w:t></w:r></w:p></w:tc><w:tc><w:tcPr><w:tcW w:w="5103" w:type="dxa"/><w:vAlign w:val="center"/></w:tcPr><w:p w14:paraId="7C5F51D8" w14:textId="71D3942E" w:rsidR="00BB2E34" w:rsidRDefault="00BB2E34" w:rsidP="00BB2E34"><w:pPr><w:jc w:val="center"/></w:pPr><w:r w:rsidRPr="002C1B5F"><w:t>CloudWatch logs capture all events for auditing</w:t></w:r></w:p></w:tc></w:tr></w:tbl><w:p w14:paraId="08FF5F9B" w14:textId="77777777" w:rsidR="00BB2E34" w:rsidRPr="002C1B5F" w:rsidRDefault="00BB2E34" w:rsidP="002C1B5F"/></w:tc><w:tc><w:tcPr><w:tcW w:w="36" w:type="dxa"/><w:vAlign w:val="center"/></w:tcPr><w:p w14:paraId="4803647F" w14:textId="77777777" w:rsidR="00BB2E34" w:rsidRPr="002C1B5F" w:rsidRDefault="00BB2E34" w:rsidP="002C1B5F"/></w:tc></w:tr><w:tr w:rsidR="00BB2E34" w:rsidRPr="002C1B5F" w14:paraId="78720F3D" w14:textId="77777777" w:rsidTr="00F7639B"><w:trPr><w:tblCellSpacing w:w="15" w:type="dxa"/></w:trPr><w:tc><w:tcPr><w:tcW w:w="8900" w:type="dxa"/><w:vAlign w:val="center"/></w:tcPr><w:p w14:paraId="2F3B90CF" w14:textId="4ABF8A06" w:rsidR="00BB2E34" w:rsidRPr="002C1B5F" w:rsidRDefault="00BB2E34" w:rsidP="00BB2E34"><w:pPr><w:jc w:val="center"/><w:rPr><w:b/><w:bCs/></w:rPr></w:pPr><w:r w:rsidRPr="007D49D4"><w:rPr><w:noProof/></w:rPr><w:drawing><wp:inline distT="0" distB="0" distL="0" distR="0" wp14:anchorId="311EF38E" wp14:editId="0B724D3B"><wp:extent cx="5731510" cy="4524375"/><wp:effectExtent l="0" t="0" r="2540" b="9525"/><wp:docPr id="861433845" name="Picture 1"/><wp:cNvGraphicFramePr><a:graphicFrameLocks xmlns:a="http://schemas.openxmlformats.org/drawingml/2006/main" noChangeAspect="1"/></wp:cNvGraphicFramePr><a:graphic xmlns:a="http://schemas.openxmlformats.org/drawingml/2006/main"><a:graphicData uri="http://schemas.openxmlformats.org/drawingml/2006/picture"><pic:pic xmlns:pic="http://schemas.openxmlformats.org/drawingml/2006/picture"><pic:nvPicPr><pic:cNvPr id="861433845" name=""/><pic:cNvPicPr/></pic:nvPicPr><pic:blipFill><a:blip r:embed="rId11"/><a:stretch><a:fillRect/></a:stretch></pic:blipFill><pic:spPr><a:xfrm><a:off x="0" y="0"/><a:ext cx="5731510" cy="4524375"/></a:xfrm><a:prstGeom prst="rect"><a:avLst/></a:prstGeom></pic:spPr></pic:pic></a:graphicData></a:graphic></wp:inline></w:drawing></w:r></w:p></w:tc><w:tc><w:tcPr><w:tcW w:w="36" w:type="dxa"/><w:vAlign w:val="center"/></w:tcPr><w:p w14:paraId="1B2F162A" w14:textId="77777777" w:rsidR="00BB2E34" w:rsidRPr="002C1B5F" w:rsidRDefault="00BB2E34" w:rsidP="002C1B5F"/></w:tc></w:tr><w:tr w:rsidR="00F7639B" w:rsidRPr="002C1B5F" w14:paraId="4F82FC6A" w14:textId="77777777" w:rsidTr="00F7639B"><w:trPr><w:tblCellSpacing w:w="15" w:type="dxa"/></w:trPr><w:tc><w:tcPr><w:tcW w:w="8900" w:type="dxa"/><w:vAlign w:val="center"/></w:tcPr><w:p w14:paraId="0073E6B1" w14:textId="545BB4FE" w:rsidR="00F7639B" w:rsidRPr="007D49D4" w:rsidRDefault="00F7639B" w:rsidP="00BB2E34"><w:pPr><w:jc w:val="center"/></w:pPr><w:r w:rsidRPr="00F7639B"><w:rPr><w:noProof/></w:rPr><w:drawing><wp:inline distT="0" distB="0" distL="0" distR="0" wp14:anchorId="5D3B5A2D" wp14:editId="48FF4B63"><wp:extent cx="5731510" cy="2589530"/><wp:effectExtent l="0" t="0" r="2540" b="1270"/><wp:docPr id="855848640" name="Picture 1"/><wp:cNvGraphicFramePr><a:graphicFrameLocks xmlns:a="http://schemas.openxmlformats.org/drawingml/2006/main" noChangeAspect="1"/></wp:cNvGraphicFramePr><a:graphic xmlns:a="http://schemas.openxmlformats.org/drawingml/2006/main"><a:graphicData uri="http://schemas.openxmlformats.org/drawingml/2006/picture"><pic:pic xmlns:pic="http://schemas.openxmlformats.org/drawingml/2006/picture"><pic:nvPicPr><pic:cNvPr id="855848640" name=""/><pic:cNvPicPr/></pic:nvPicPr><pic:blipFill><a:blip r:embed="rId12"/><a:stretch><a:fillRect/></a:stretch></pic:blipFill><pic:spPr><a:xfrm><a:off x="0" y="0"/><a:ext cx="5731510" cy="2589530"/></a:xfrm><a:prstGeom prst="rect"><a:avLst/></a:prstGeom></pic:spPr></pic:pic></a:graphicData></a:graphic></wp:inline></w:drawing></w:r></w:p></w:tc><w:tc><w:tcPr><w:tcW w:w="36" w:type="dxa"/><w:vAlign w:val="center"/></w:tcPr><w:p w14:paraId="7965BFFB" w14:textId="77777777" w:rsidR="00F7639B" w:rsidRPr="002C1B5F" w:rsidRDefault="00F7639B" w:rsidP="002C1B5F"/></w:tc></w:tr></w:tbl><w:p w14:paraId="55DB1E32" w14:textId="7083C0DD" w:rsidR="002C1B5F" w:rsidRPr="002C1B5F" w:rsidRDefault="007D49D4" w:rsidP="002C1B5F"><w:r w:rsidRPr="007D49D4"><w:rPr><w:noProof/></w:rPr><w:lastRenderedPageBreak/><w:drawing><wp:inline distT="0" distB="0" distL="0" distR="0" wp14:anchorId="45107175" wp14:editId="65113F14"><wp:extent cx="5731510" cy="1814830"/><wp:effectExtent l="0" t="0" r="2540" b="0"/><wp:docPr id="741449262" name="Picture 1"/><wp:cNvGraphicFramePr><a:graphicFrameLocks xmlns:a="http://schemas.openxmlformats.org/drawingml/2006/main" noChangeAspect="1"/></wp:cNvGraphicFramePr><a:graphic xmlns:a="http://schemas.openxmlformats.org/drawingml/2006/main"><a:graphicData uri="http://schemas.openxmlformats.org/drawingml/2006/picture"><pic:pic xmlns:pic="http://schemas.openxmlformats.org/drawingml/2006/picture"><pic:nvPicPr><pic:cNvPr id="741449262" name=""/><pic:cNvPicPr/></pic:nvPicPr><pic:blipFill><a:blip r:embed="rId13"/><a:stretch><a:fillRect/></a:stretch></pic:blipFill><pic:spPr><a:xfrm><a:off x="0" y="0"/><a:ext cx="5731510" cy="1814830"/></a:xfrm><a:prstGeom prst="rect"><a:avLst/></a:prstGeom></pic:spPr></pic:pic></a:graphicData></a:graphic></wp:inline></w:drawing></w:r><w:r w:rsidR="00F7639B" w:rsidRPr="00F7639B"><w:rPr><w:noProof/></w:rPr><w:t xml:space="preserve"> </w:t></w:r><w:r w:rsidR="00F7639B" w:rsidRPr="00F7639B"><w:rPr><w:noProof/></w:rPr><w:drawing><wp:inline distT="0" distB="0" distL="0" distR="0" wp14:anchorId="5FED8CF2" wp14:editId="425747EB"><wp:extent cx="5731510" cy="2605405"/><wp:effectExtent l="0" t="0" r="2540" b="4445"/><wp:docPr id="1075505913" name="Picture 1" descr="A screenshot of a computer&#xA;&#xA;AI-generated content may be incorrect."/><wp:cNvGraphicFramePr><a:graphicFrameLocks xmlns:a="http://schemas.openxmlformats.org/drawingml/2006/main" noChangeAspect="1"/></wp:cNvGraphicFramePr><a:graphic xmlns:a="http://schemas.openxmlformats.org/drawingml/2006/main"><a:graphicData uri="http://schemas.openxmlformats.org/drawingml/2006/picture"><pic:pic xmlns:pic="http://schemas.openxmlformats.org/drawingml/2006/picture"><pic:nvPicPr><pic:cNvPr id="1075505913" name="Picture 1" descr="A screenshot of a computer&#xA;&#xA;AI-generated content may be incorrect."/><pic:cNvPicPr/></pic:nvPicPr><pic:blipFill><a:blip r:embed="rId14"/><a:stretch><a:fillRect/></a:stretch></pic:blipFill><pic:spPr><a:xfrm><a:off x="0" y="0"/><a:ext cx="5731510" cy="2605405"/></a:xfrm><a:prstGeom prst="rect"><a:avLst/></a:prstGeom></pic:spPr></pic:pic></a:graphicData></a:graphic></wp:inline></w:drawing></w:r></w:p><w:p w14:paraId="522259BA" w14:textId="77777777" w:rsidR="002C1B5F" w:rsidRPr="002C1B5F" w:rsidRDefault="002C1B5F" w:rsidP="00BB2E34"><w:pPr><w:jc w:val="center"/><w:rPr><w:b/><w:bCs/><w:sz w:val="28"/><w:szCs w:val="28"/></w:rPr></w:pPr><w:r w:rsidRPr="002C1B5F"><w:rPr><w:b/><w:bCs/><w:sz w:val="28"/><w:szCs w:val="28"/><w:highlight w:val="yellow"/></w:rPr><w:t>Challenges Faced</w:t></w:r></w:p><w:p w14:paraId="0AD90E30" w14:textId="77777777" w:rsidR="002C1B5F" w:rsidRPr="002C1B5F" w:rsidRDefault="002C1B5F" w:rsidP="002C1B5F"><w:pPr><w:numPr><w:ilvl w:val="0"/><w:numId w:val="8"/></w:numPr></w:pPr><w:r w:rsidRPr="002C1B5F"><w:t>Encountered IAM permission errors → resolved by updating policies to include S3 and RDS access.</w:t></w:r></w:p><w:p w14:paraId="609AF8E2" w14:textId="0A0FD072" w:rsidR="00B60AEE" w:rsidRDefault="002C1B5F" w:rsidP="00BB2E34"><w:pPr><w:numPr><w:ilvl w:val="0"/><w:numId w:val="8"/></w:numPr></w:pPr><w:r w:rsidRPr="002C1B5F"><w:t>Tested CSV parsing logic to handle edge cases and malformed data.</w:t></w:r></w:p><w:p w14:paraId="1C6824A5" w14:textId="77777777" w:rsidR="002C1B5F" w:rsidRPr="002C1B5F" w:rsidRDefault="0031267B" w:rsidP="002C1B5F"><w:r><w:pict w14:anchorId="5CAFD056"><v:rect id="_x0000_i1035" style="width:0;height:1.5pt" o:hralign="center" o:hrstd="t" o:hr="t" fillcolor="#a0a0a0" stroked="f"/></w:pict></w:r></w:p><w:p w14:paraId="0BD6B7E3" w14:textId="47592441" w:rsidR="00B60AEE" w:rsidRPr="002C1B5F" w:rsidRDefault="002C1B5F" w:rsidP="00BB2E34"><w:pPr><w:jc w:val="center"/><w:rPr><w:b/><w:bCs/><w:sz w:val="28"/><w:szCs w:val="28"/></w:rPr></w:pPr><w:r w:rsidRPr="002C1B5F"><w:rPr><w:b/><w:bCs/><w:sz w:val="28"/><w:szCs w:val="28"/><w:highlight w:val="yellow"/></w:rPr><w:t>Lessons Learned</w:t></w:r></w:p><w:p w14:paraId="1612CB51" w14:textId="77777777" w:rsidR="002C1B5F" w:rsidRPr="002C1B5F" w:rsidRDefault="002C1B5F" w:rsidP="002C1B5F"><w:pPr><w:numPr><w:ilvl w:val="0"/><w:numId w:val="9"/></w:numPr></w:pPr><w:r w:rsidRPr="002C1B5F"><w:t>Learned to build an event-driven pipeline using AWS services.</w:t></w:r></w:p><w:p w14:paraId="6A0E9F7D" w14:textId="77777777" w:rsidR="002C1B5F" w:rsidRPr="002C1B5F" w:rsidRDefault="002C1B5F" w:rsidP="002C1B5F"><w:pPr><w:numPr><w:ilvl w:val="0"/><w:numId w:val="9"/></w:numPr></w:pPr><w:r w:rsidRPr="002C1B5F"><w:t>Understood the importance of proper IAM roles and security.</w:t></w:r></w:p><w:p w14:paraId="4E098009" w14:textId="77777777" w:rsidR="002C1B5F" w:rsidRPr="002C1B5F" w:rsidRDefault="002C1B5F" w:rsidP="002C1B5F"><w:pPr><w:numPr><w:ilvl w:val="0"/><w:numId w:val="9"/></w:numPr></w:pPr><w:r w:rsidRPr="002C1B5F"><w:t>Gained hands-on experience integrating S3, Lambda, RDS, SNS, and CloudWatch.</w:t></w:r></w:p><w:p w14:paraId="5D81BC40" w14:textId="77777777" w:rsidR="002C1B5F" w:rsidRPr="002C1B5F" w:rsidRDefault="002C1B5F" w:rsidP="002C1B5F"><w:pPr><w:numPr><w:ilvl w:val="0"/><w:numId w:val="9"/></w:numPr></w:pPr><w:r w:rsidRPr="002C1B5F"><w:t>Improved Python scripting for AWS service automation.</w:t></w:r></w:p><w:p w14:paraId="551FBB11" w14:textId="77777777" w:rsidR="002C1B5F" w:rsidRPr="002C1B5F" w:rsidRDefault="0031267B" w:rsidP="002C1B5F"><w:r><w:pict w14:anchorId="5FD84F67"><v:rect id="_x0000_i1036" style="width:0;height:1.5pt" o:hralign="center" o:hrstd="t" o:hr="t" fillcolor="#a0a0a0" stroked="f"/></w:pict></w:r></w:p><w:p w14:paraId="3D585085" w14:textId="77777777" w:rsidR="002C1B5F" w:rsidRPr="002C1B5F" w:rsidRDefault="002C1B5F" w:rsidP="00BB2E34"><w:pPr><w:jc w:val="center"/><w:rPr><w:b/><w:bCs/><w:sz w:val="28"/><w:szCs w:val="28"/></w:rPr></w:pPr><w:r w:rsidRPr="002C1B5F"><w:rPr><w:b/><w:bCs/><w:sz w:val="28"/><w:szCs w:val="28"/><w:highlight w:val="yellow"/></w:rPr><w:t>Conclusion</w:t></w:r></w:p><w:p w14:paraId="0015D3E4" w14:textId="77777777" w:rsidR="002C1B5F" w:rsidRPr="002C1B5F" w:rsidRDefault="002C1B5F" w:rsidP="002C1B5F"><w:r w:rsidRPr="002C1B5F"><w:lastRenderedPageBreak/><w:t>This project successfully implemented an automated, event-driven data ingestion pipeline on AWS.</w:t></w:r></w:p><w:p w14:paraId="606E6F93" w14:textId="77777777" w:rsidR="002C1B5F" w:rsidRPr="002C1B5F" w:rsidRDefault="002C1B5F" w:rsidP="002C1B5F"><w:pPr><w:numPr><w:ilvl w:val="0"/><w:numId w:val="10"/></w:numPr></w:pPr><w:r w:rsidRPr="002C1B5F"><w:t>Files uploaded from a local machine are processed and inserted into RDS in real-time.</w:t></w:r></w:p><w:p w14:paraId="07BB3884" w14:textId="77777777" w:rsidR="002C1B5F" w:rsidRPr="002C1B5F" w:rsidRDefault="002C1B5F" w:rsidP="002C1B5F"><w:pPr><w:numPr><w:ilvl w:val="0"/><w:numId w:val="10"/></w:numPr></w:pPr><w:r w:rsidRPr="002C1B5F"><w:t>Notifications are automatically sent via SNS.</w:t></w:r></w:p><w:p w14:paraId="3473E676" w14:textId="77777777" w:rsidR="002C1B5F" w:rsidRPr="002C1B5F" w:rsidRDefault="002C1B5F" w:rsidP="002C1B5F"><w:pPr><w:numPr><w:ilvl w:val="0"/><w:numId w:val="10"/></w:numPr></w:pPr><w:r w:rsidRPr="002C1B5F"><w:t>CloudWatch logs track all activity for monitoring and debugging.</w:t></w:r></w:p><w:p w14:paraId="5D5D13C8" w14:textId="77777777" w:rsidR="002C1B5F" w:rsidRPr="002C1B5F" w:rsidRDefault="002C1B5F" w:rsidP="002C1B5F"><w:r w:rsidRPr="002C1B5F"><w:t>The solution demonstrates a secure, scalable, and reliable architecture for enterprise-level automated data ingestion.</w:t></w:r></w:p><w:p w14:paraId="3CBB5673" w14:textId="22395018" w:rsidR="000C02DD" w:rsidRPr="002C1B5F" w:rsidRDefault="000C02DD" w:rsidP="002C1B5F"/><w:sectPr w:rsidR="000C02DD" w:rsidRPr="002C1B5F"><w:pgSz w:w="11906" w:h="16838"/><w:pgMar w:top="1440" w:right="1440" w:bottom="1440" w:left="1440" w:header="708" w:footer="708" w:gutter="0"/><w:cols w:space="708"/><w:docGrid w:linePitch="360"/></w:sectPr></w:body></w:document>